{
"type": "FeatureCollection",
"crs": { "type": "name", "properties": { "name": "urn:ogc:def:crs:OGC:1.3:CRS84" } },
                                                                                
"features": [
{ "type": "Feature", "properties": { "OID_": 0, "PageName": "W40", "PageNumber": 1329, "Shape_Leng": 120000.0, "Shape_Area": 900000000.0, "gov": "GOV1", "dist": "GOV1_W", "sd": "W40", "Nahya_EN": "W40" }, "geometry": { "type": "Polygon", "coordinates": [ [ [ 35.8, 36.7 ], [ 35.8, 36.9 ], [ 36.1, 36.9 ], [ 36.1, 36.7 ], [ 35.8, 36.7 ] ] ] } },
{ "type": "Feature", "properties": { "OID_": 0, "PageName": "W41", "PageNumber": 1330, "Shape_Leng": 120000.0, "Shape_Area": 900000000.0, "gov": "GOV1", "dist": "GOV1_W", "sd": "W41", "Nahya_EN": "W41" }, "geometry": { "type": "Polygon", "coordinates": [ [ [ 36.1, 36.7 ], [ 36.1, 36.9 ], [ 36.5, 37.0 ], [ 36.5, 36.7 ], [ 36.1, 36.7 ] ] ] } },
{ "type": "Feature", "properties": { "OID_": 0, "PageName": "W42", "PageNumber": 1331, "Shape_Leng": 120000.0, "Shape_Area": 900000000.0, "gov": "GOV1", "dist": "GOV1_W", "sd": "W42", "Nahya_EN": "W42" }, "geometry": { "type": "Polygon", "coordinates": [ [ [ 36.5, 36.7 ], [ 36.5, 37.0 ], [ 36.8, 37.0 ], [ 36.8, 36.7 ], [ 36.5, 36.7 ] ] ] } },
{ "type": "Feature", "properties": { "OID_": 0, "PageName": "W43", "PageNumber": 1332, "Shape_Leng": 120000.0, "Shape_Area": 900000000.0, "gov": "GOV1", "dist": "GOV1_W", "sd": "W43", "Nahya_EN": "W43" }, "geometry": { "type": "Polygon", "coordinates": [ [ [ 36.8, 36.7 ], [ 36.8, 37.0 ], [ 37.1, 37.0 ], [ 37.1, 36.7 ], [ 36.8, 36.7 ] ] ] } },
{ "type": "Feature", "properties": { "OID_": 0, "PageName": "W44", "PageNumber": 1333, "Shape_Leng": 120000.0, "Shape_Area": 900000000.0, "gov": "GOV1", "dist": "GOV1_W", "sd": "W44", "Nahya_EN": "W44" }, "geometry": { "type": "Polygon", "coordinates": [ [ [ 37.1, 36.7 ], [ 37.1, 37.0 ], [ 37.5, 37.0 ], [ 37.5, 36.7 ], [ 37.1, 36.7 ] ] ] } },
{ "type": "Feature", "properties": { "OID_": 0, "PageName": "W45", "PageNumber": 1334, "Shape_Leng": 120000.0, "Shape_Area": 900000000.0, "gov": "GOV1", "dist": "GOV1_W", "sd": "W45", "Nahya_EN": "W45" }, "geometry": { "type": "Polygon", "coordinates": [ [ [ 37.5, 36.7 ], [ 37.5, 37.0 ], [ 37.8, 37.0 ], [ 37.8, 36.7 ], [ 37.5, 36.7 ] ] ] } },
{ "type": "Feature", "properties": { "OID_": 0, "PageName": "W46", "PageNumber": 1335, "Shape_Leng": 120000.0, "Shape_Area": 900000000.0, "gov": "GOV1", "dist": "GOV1_W", "sd": "W46", "Nahya_EN": "W46" }, "geometry": { "type": "Polygon", "coordinates": [ [ [ 37.8, 36.7 ], [ 37.8, 37.0 ], [ 38.2, 37.0 ], [ 38.2, 36.7 ], [ 37.8, 36.7 ] ] ] } },
{ "type": "Feature", "properties": { "OID_": 0, "PageName": "W47", "PageNumber": 1336, "Shape_Leng": 120000.0, "Shape_Area": 900000000.0, "gov": "GOV1", "dist": "GOV1_W", "sd": "W47", "Nahya_EN": "W47" }, "geometry": { "type": "Polygon", "coordinates": [ [ [ 38.2, 36.7 ], [ 38.2, 37.0 ], [ 38.5, 37.0 ], [ 38.5, 36.7 ], [ 38.2, 36.7 ] ] ] } },
{ "type": "Feature", "properties": { "OID_": 0, "PageName": "W48", "PageNumber": 1337, "Shape_Leng": 120000.0, "Shape_Area": 900000000.0, "gov": "GOV1", "dist": "GOV1_W", "sd": "W48", "Nahya_EN": "W48" }, "geometry": { "type": "Polygon", "coordinates": [ [ [ 38.5, 36.7 ], [ 38.5, 37.0 ], [ 38.8, 37.0 ], [ 38.8, 36.7 ], [ 38.5, 36.7 ] ] ] } },
{ "type": "Feature", "properties": { "OID_": 0, "PageName": "W49", "PageNumber": 1338, "Shape_Leng": 120000.0, "Shape_Area": 900000000.0, "gov": "GOV1", "dist": "GOV1_W", "sd": "W49", "Nahya_EN": "W49" }, "geometry": { "type": "Polygon", "coordinates": [ [ [ 38.8, 36.7 ], [ 38.8, 37.0 ], [ 39.2, 37.0 ], [ 39.2, 36.7 ], [ 38.8, 36.7 ] ] ] } },
{ "type": "Feature", "properties": { "OID_": 0, "PageName": "W50", "PageNumber": 1339, "Shape_Leng": 120000.0, "Shape_Area": 900000000.0, "gov": "GOV2", "dist": "GOV2_W", "sd": "W50", "Nahya_EN": "W50" }, "geometry": { "type": "Polygon", "coordinates": [ [ [ 39.2, 36.7 ], [ 39.2, 37.0 ], [ 39.5, 37.0 ], [ 39.5, 36.7 ], [ 39.2, 36.7 ] ] ] } },
{ "type": "Feature", "properties": { "OID_": 0, "PageName": "W51", "PageNumber": 1340, "Shape_Leng": 120000.0, "Shape_Area": 900000000.0, "gov": "GOV2", "dist": "GOV2_W", "sd": "W51", "Nahya_EN": "W51" }, "geometry": { "type": "Polygon", "coordinates": [ [ [ 39.5, 36.7 ], [ 39.5, 37.0 ], [ 39.8, 37.0 ], [ 39.8, 36.7 ], [ 39.5, 36.7 ] ] ] } },
{ "type": "Feature", "properties": { "OID_": 0, "PageName": "W52", "PageNumber": 1341, "Shape_Leng": 120000.0, "Shape_Area": 900000000.0, "gov": "GOV2", "dist": "GOV2_W", "sd": "W52", "Nahya_EN": "W52" }, "geometry": { "type": "Polygon", "coordinates": [ [ [ 39.8, 36.7 ], [ 39.8, 37.0 ], [ 40.2, 37.0 ], [ 40.2, 36.7 ], [ 39.8, 36.7 ] ] ] } },
{ "type": "Feature", "properties": { "OID_": 0, "PageName": "W53", "PageNumber": 1342, "Shape_Leng": 120000.0, "Shape_Area": 900000000.0, "gov": "GOV2", "dist": "GOV2_W", "sd": "W53", "Nahya_EN": "W53" }, "geometry": { "type": "Polygon", "coordinates": [ [ [ 40.2, 36.7 ], [ 40.2, 37.0 ], [ 40.5, 37.0 ], [ 40.5, 36.7 ], [ 40.2, 36.7 ] ] ] } },
{ "type": "Feature", "properties": { "OID_": 0, "PageName": "W54", "PageNumber": 1343, "Shape_Leng": 120000.0, "Shape_Area": 900000000.0, "gov": "GOV2", "dist": "GOV2_W", "sd": "W54", "Nahya_EN": "W54" }, "geometry": { "type": "Polygon", "coordinates": [ [ [ 40.5, 36.7 ], [ 40.5, 37.0 ], [ 40.8, 37.0 ], [ 40.8, 36.7 ], [ 40.5, 36.7 ] ] ] } },
{ "type": "Feature", "properties": { "OID_": 0, "PageName": "W55", "PageNumber": 1344, "Shape_Leng": 120000.0, "Shape_Area": 900000000.0, "gov": "GOV2", "dist": "GOV2_W", "sd": "W55", "Nahya_EN": "W55" }, "geometry": { "type": "Polygon", "coordinates": [ [ [ 40.8, 36.7 ], [ 40.8, 37.0 ], [ 41.2, 37.0 ], [ 41.2, 36.7 ], [ 40.8, 36.7 ] ] ] } },
{ "type": "Feature", "properties": { "OID_": 0, "PageName": "W56", "PageNumber": 1345, "Shape_Leng": 120000.0, "Shape_Area": 900000000.0, "gov": "GOV2", "dist": "GOV2_W", "sd": "W56", "Nahya_EN": "W56" }, "geometry": { "type": "Polygon", "coordinates": [ [ [ 41.2, 36.7 ], [ 41.2, 37.0 ], [ 41.5, 37.0 ], [ 41.5, 36.7 ], [ 41.2, 36.7 ] ] ] } },
{ "type": "Feature", "properties": { "OID_": 0, "PageName": "W57", "PageNumber": 1346, "Shape_Leng": 120000.0, "Shape_Area": 900000000.0, "gov": "GOV2", "dist": "GOV2_W", "sd": "W57", "Nahya_EN": "W57" }, "geometry": { "type": "Polygon", "coordinates": [ [ [ 41.5, 36.7 ], [ 41.5, 37.0 ], [ 41.9, 36.9 ], [ 41.8, 36.7 ], [ 41.5, 36.7 ] ] ] } },
{ "type": "Feature", "properties": { "OID_": 0, "PageName": "W58", "PageNumber": 1347, "Shape_Leng": 120000.0, "Shape_Area": 900000000.0, "gov": "GOV2", "dist": "GOV2_W", "sd": "W58", "Nahya_EN": "W58" }, "geometry": { "type": "Polygon", "coordinates": [ [ [ 41.8, 36.7 ], [ 41.9, 36.9 ], [ 42.2, 36.9 ], [ 42.2, 36.7 ], [ 41.8, 36.7 ] ] ] } },
{ "type": "Feature", "properties": { "OID_": 0, "PageName": "X40", "PageNumber": 1422, "Shape_Leng": 120000.0, "Shape_Area": 900000000.0, "gov": "GOV1", "dist": "GOV1_X", "sd": "X40", "Nahya_EN": "X40" }, "geometry": { "type": "Polygon", "coordinates": [ [ [ 35.8, 36.4 ], [ 35.8, 36.7 ], [ 36.1, 36.7 ], [ 36.2, 36.4 ], [ 35.8, 36.4 ] ] ] } },
{ "type": "Feature", "properties": { "OID_": 0, "PageName": "X41", "PageNumber": 1423, "Shape_Leng": 120000.0, "Shape_Area": 900000000.0, "gov": "GOV1", "dist": "GOV1_X", "sd": "X41", "Nahya_EN": "X41" }, "geometry": { "type": "Polygon", "coordinates": [ [ [ 36.2, 36.4 ], [ 36.1, 36.7 ], [ 36.5, 36.7 ], [ 36.5, 36.4 ], [ 36.2, 36.4 ] ] ] } },
{ "type": "Feature", "properties": { "OID_": 0, "PageName": "X42", "PageNumber": 1424, "Shape_Leng": 120000.0, "Shape_Area": 900000000.0, "gov": "GOV1", "dist": "GOV1_X", "sd": "X42", "Nahya_EN": "X42" }, "geometry": { "type": "Polygon", "coordinates": [ [ [ 36.5, 36.4 ], [ 36.5, 36.7 ], [ 36.8, 36.7 ], [ 36.8, 36.4 ], [ 36.5, 36.4 ] ] ] } },
{ "type": "Feature", "properties": { "OID_": 0, "PageName": "X43", "PageNumber": 1425, "Shape_Leng": 120000.0, "Shape_Area": 900000000.0, "gov": "GOV1", "dist": "GOV1_X", "sd": "X43", "Nahya_EN": "X43" }, "geometry": { "type": "Polygon", "coordinates": [ [ [ 36.8, 36.4 ], [ 36.8, 36.7 ], [ 37.1, 36.7 ], [ 37.2, 36.4 ], [ 36.8, 36.4 ] ] ] } },
{ "type": "Feature", "properties": { "OID_": 0, "PageName": "X44", "PageNumber": 1426, "Shape_Leng": 120000.0, "Shape_Area": 900000000.0, "gov": "GOV1", "dist": "GOV1_X", "sd": "X44", "Nahya_EN": "X44" }, "geometry": { "type": "Polygon", "coordinates": [ [ [ 37.2, 36.4 ], [ 37.1, 36.7 ], [ 37.5, 36.7 ], [ 37.5, 36.4 ], [ 37.2, 36.4 ] ] ] } },
{ "type": "Feature", "properties": { "OID_": 0, "PageName": "X45", "PageNumber": 1427, "Shape_Leng": 120000.0, "Shape_Area": 900000000.0, "gov": "GOV1", "dist": "GOV1_X", "sd": "X45", "Nahya_EN": "X45" }, "geometry": { "type": "Polygon", "coordinates": [ [ [ 37.5, 36.4 ], [ 37.5, 36.7 ], [ 37.8, 36.7 ], [ 37.8, 36.4 ], [ 37.5, 36.4 ] ] ] } },
{ "type": "Feature", "properties": { "OID_": 0, "PageName": "X46", "PageNumber": 1428, "Shape_Leng": 120000.0, "Shape_Area": 900000000.0, "gov": "GOV1", "dist": "GOV1_X", "sd": "X46", "Nahya_EN": "X46" }, "geometry": { "type": "Polygon", "coordinates": [ [ [ 37.8, 36.4 ], [ 37.8, 36.7 ], [ 38.2, 36.7 ], [ 38.2, 36.4 ], [ 37.8, 36.4 ] ] ] } },
{ "type": "Feature", "properties": { "OID_": 0, "PageName": "X47", "PageNumber": 1429, "Shape_Leng": 120000.0, "Shape_Area": 900000000.0, "gov": "GOV1", "dist": "GOV1_X", "sd": "X47", "Nahya_EN": "X47" }, "geometry": { "type": "Polygon", "coordinates": [ [ [ 38.2, 36.4 ], [ 38.2, 36.7 ], [ 38.5, 36.7 ], [ 38.5, 36.4 ], [ 38.2, 36.4 ] ] ] } },
{ "type": "Feature", "properties": { "OID_": 0, "PageName": "X48", "PageNumber": 1430, "Shape_Leng": 120000.0, "Shape_Area": 900000000.0, "gov": "GOV1", "dist": "GOV1_X", "sd": "X48", "Nahya_EN": "X48" }, "geometry": { "type": "Polygon", "coordinates": [ [ [ 38.5, 36.4 ], [ 38.5, 36.7 ], [ 38.8, 36.7 ], [ 38.8, 36.4 ], [ 38.5, 36.4 ] ] ] } },
{ "type": "Feature", "properties": { "OID_": 0, "PageName": "X49", "PageNumber": 1431, "Shape_Leng": 120000.0, "Shape_Area": 900000000.0, "gov": "GOV1", "dist": "GOV1_X", "sd": "X49", "Nahya_EN": "X49" }, "geometry": { "type": "Polygon", "coordinates": [ [ [ 38.8, 36.4 ], [ 38.8, 36.7 ], [ 39.2, 36.7 ], [ 39.2, 36.4 ], [ 38.8, 36.4 ] ] ] } },
{ "type": "Feature", "properties": { "OID_": 0, "PageName": "X50", "PageNumber": 1432, "Shape_Leng": 120000.0, "Shape_Area": 900000000.0, "gov": "GOV2", "dist": "GOV2_X", "sd": "X50", "Nahya_EN": "X50" }, "geometry": { "type": "Polygon", "coordinates": [ [ [ 39.2, 36.4 ], [ 39.2, 36.7 ], [ 39.5, 36.7 ], [ 39.5, 36.4 ], [ 39.2, 36.4 ] ] ] } },
{ "type": "Feature", "properties": { "OID_": 0, "PageName": "X51", "PageNumber": 1433, "Shape_Leng": 120000.0, "Shape_Area": 900000000.0, "gov": "GOV2", "dist": "GOV2_X", "sd": "X51", "Nahya_EN": "X51" }, "geometry": { "type": "Polygon", "coordinates": [ [ [ 39.5, 36.4 ], [ 39.5, 36.7 ], [ 39.8, 36.7 ], [ 39.8, 36.4 ], [ 39.5, 36.4 ] ] ] } },
{ "type": "Feature", "properties": { "OID_": 0, "PageName": "X52", "PageNumber": 1434, "Shape_Leng": 120000.0, "Shape_Area": 900000000.0, "gov": "GOV2", "dist": "GOV2_X", "sd": "X52", "Nahya_EN": "X52" }, "geometry": { "type": "Polygon", "coordinates": [ [ [ 39.8, 36.4 ], [ 39.8, 36.7 ], [ 40.2, 36.7 ], [ 40.2, 36.4 ], [ 39.8, 36.4 ] ] ] } },
{ "type": "Feature", "properties": { "OID_": 0, "PageName": "X53", "PageNumber": 1435, "Shape_Leng": 120000.0, "Shape_Area": 900000000.0, "gov": "GOV2", "dist": "GOV2_X", "sd": "X53", "Nahya_EN": "X53" }, "geometry": { "type": "Polygon", "coordinates": [ [ [ 40.2, 36.4 ], [ 40.2, 36.7 ], [ 40.5, 36.7 ], [ 40.5, 36.4 ], [ 40.2, 36.4 ] ] ] } },
{ "type": "Feature", "properties": { "OID_": 0, "PageName": "X54", "PageNumber": 1436, "Shape_Leng": 120000.0, "Shape_Area": 900000000.0, "gov": "GOV2", "dist": "GOV2_X", "sd": "X54", "Nahya_EN": "X54" }, "geometry": { "type": "Polygon", "coordinates": [ [ [ 40.5, 36.4 ], [ 40.5, 36.7 ], [ 40.8, 36.7 ], [ 40.8, 36.4 ], [ 40.5, 36.4 ] ] ] } },
{ "type": "Feature", "properties": { "OID_": 0, "PageName": "X55", "PageNumber": 1437, "Shape_Leng": 120000.0, "Shape_Area": 900000000.0, "gov": "GOV2", "dist": "GOV2_X", "sd": "X55", "Nahya_EN": "X55" }, "geometry": { "type": "Polygon", "coordinates": [ [ [ 40.8, 36.4 ], [ 40.8, 36.7 ], [ 41.2, 36.7 ], [ 41.2, 36.4 ], [ 40.8, 36.4 ] ] ] } },
{ "type": "Feature", "properties": { "OID_": 0, "PageName": "X56", "PageNumber": 1438, "Shape_Leng": 120000.0, "Shape_Area": 900000000.0, "gov": "GOV2", "dist": "GOV2_X", "sd": "X56", "Nahya_EN": "X56" }, "geometry": { "type": "Polygon", "coordinates": [ [ [ 41.2, 36.4 ], [ 41.2, 36.7 ], [ 41.5, 36.7 ], [ 41.5, 36.4 ], [ 41.2, 36.4 ] ] ] } },
{ "type": "Feature", "properties": { "OID_": 0, "PageName": "X57", "PageNumber": 1439, "Shape_Leng": 120000.0, "Shape_Area": 900000000.0, "gov": "GOV2", "dist": "GOV2_X", "sd": "X57", "Nahya_EN": "X57" }, "geometry": { "type": "Polygon", "coordinates": [ [ [ 41.5, 36.4 ], [ 41.5, 36.7 ], [ 41.8, 36.7 ], [ 41.8, 36.4 ], [ 41.5, 36.4 ] ] ] } },
{ "type": "Feature", "properties": { "OID_": 0, "PageName": "X58", "PageNumber": 1440, "Shape_Leng": 120000.0, "Shape_Area": 900000000.0, "gov": "GOV2", "dist": "GOV2_X", "sd": "X58", "Nahya_EN": "X58" }, "geometry": { "type": "Polygon", "coordinates": [ [ [ 41.8, 36.4 ], [ 41.8, 36.7 ], [ 42.2, 36.7 ], [ 42.2, 36.4 ], [ 41.8, 36.4 ] ] ] } },
{ "type": "Feature", "properties": { "OID_": 0, "PageName": "Y40", "PageNumber": 1507, "Shape_Leng": 120000.0, "Shape_Area": 900000000.0, "gov": "GOV1", "dist": "GOV1_Y", "sd": "Y40", "Nahya_EN": "Y40" }, "geometry": { "type": "Polygon", "coordinates": [ [ [ 35.8, 36.1 ], [ 35.8, 36.4 ], [ 36.2, 36.4 ], [ 36.2, 36.1 ], [ 35.8, 36.1 ] ] ] } },
{ "type": "Feature", "properties": { "OID_": 0, "PageName": "Y41", "PageNumber": 1508, "Shape_Leng": 120000.0, "Shape_Area": 900000000.0, "gov": "GOV1", "dist": "GOV1_Y", "sd": "Y41", "Nahya_EN": "Y41" }, "geometry": { "type": "Polygon", "coordinates": [ [ [ 36.2, 36.1 ], [ 36.2, 36.4 ], [ 36.5, 36.4 ], [ 36.5, 36.1 ], [ 36.2, 36.1 ] ] ] } },
{ "type": "Feature", "properties": { "OID_": 0, "PageName": "Y42", "PageNumber": 1509, "Shape_Leng": 120000.0, "Shape_Area": 900000000.0, "gov": "GOV1", "dist": "GOV1_Y", "sd": "Y42", "Nahya_EN": "Y42" }, "geometry": { "type": "Polygon", "coordinates": [ [ [ 36.5, 36.1 ], [ 36.5, 36.4 ], [ 36.8, 36.4 ], [ 36.8, 36.1 ], [ 36.5, 36.1 ] ] ] } },
{ "type": "Feature", "properties": { "OID_": 0, "PageName": "Y43", "PageNumber": 1510, "Shape_Leng": 120000.0, "Shape_Area": 900000000.0, "gov": "GOV1", "dist": "GOV1_Y", "sd": "Y43", "Nahya_EN": "Y43" }, "geometry": { "type": "Polygon", "coordinates": [ [ [ 36.8, 36.1 ], [ 36.8, 36.4 ], [ 37.2, 36.4 ], [ 37.2, 36.2 ], [ 36.8, 36.1 ] ] ] } },
{ "type": "Feature", "properties": { "OID_": 0, "PageName": "Y44", "PageNumber": 1511, "Shape_Leng": 120000.0, "Shape_Area": 900000000.0, "gov": "GOV1", "dist": "GOV1_Y", "sd": "Y44", "Nahya_EN": "Y44" }, "geometry": { "type": "Polygon", "coordinates": [ [ [ 37.2, 36.2 ], [ 37.2, 36.4 ], [ 37.5, 36.4 ], [ 37.5, 36.2 ], [ 37.2, 36.2 ] ] ] } },
{ "type": "Feature", "properties": { "OID_": 0, "PageName": "Y45", "PageNumber": 1512, "Shape_Leng": 120000.0, "Shape_Area": 900000000.0, "gov": "GOV1", "dist": "GOV1_Y", "sd": "Y45", "Nahya_EN": "Y45" }, "geometry": { "type": "Polygon", "coordinates": [ [ [ 37.5, 36.2 ], [ 37.5, 36.4 ], [ 37.8, 36.4 ], [ 37.8, 36.2 ], [ 37.5, 36.2 ] ] ] } },
{ "type": "Feature", "properties": { "OID_": 0, "PageName": "Y46", "PageNumber": 1513, "Shape_Leng": 120000.0, "Shape_Area": 900000000.0, "gov": "GOV1", "dist": "GOV1_Y", "sd": "Y46", "Nahya_EN": "Y46" }, "geometry": { "type": "Polygon", "coordinates": [ [ [ 37.8, 36.2 ], [ 37.8, 36.4 ], [ 38.2, 36.4 ], [ 38.2, 36.2 ], [ 37.8, 36.2 ] ] ] } },
{ "type": "Feature", "properties": { "OID_": 0, "PageName": "Y47", "PageNumber": 1514, "Shape_Leng": 120000.0, "Shape_Area": 900000000.0, "gov": "GOV1", "dist": "GOV1_Y", "sd": "Y47", "Nahya_EN": "Y47" }, "geometry": { "type": "Polygon", "coordinates": [ [ [ 38.2, 36.2 ], [ 38.2, 36.4 ], [ 38.5, 36.4 ], [ 38.5, 36.2 ], [ 38.2, 36.2 ] ] ] } },
{ "type": "Feature", "properties": { "OID_": 0, "PageName": "Y48", "PageNumber": 1515, "Shape_Leng": 120000.0, "Shape_Area": 900000000.0, "gov": "GOV1", "dist": "GOV1_Y", "sd": "Y48", "Nahya_EN": "Y48" }, "geometry": { "type": "Polygon", "coordinates": [ [ [ 38.5, 36.2 ], [ 38.5, 36.4 ], [ 38.8, 36.4 ], [ 38.8, 36.2 ], [ 38.5, 36.2 ] ] ] } },
{ "type": "Feature", "properties": { "OID_": 0, "PageName": "Y49", "PageNumber": 1516, "Shape_Leng": 120000.0, "Shape_Area": 900000000.0, "gov": "GOV1", "dist": "GOV1_Y", "sd": "Y49", "Nahya_EN": "Y49" }, "geometry": { "type": "Polygon", "coordinates": [ [ [ 38.8, 36.2 ], [ 38.8, 36.4 ], [ 39.2, 36.4 ], [ 39.2, 36.2 ], [ 38.8, 36.2 ] ] ] } },
{ "type": "Feature", "properties": { "OID_": 0, "PageName": "Y50", "PageNumber": 1517, "Shape_Leng": 120000.0, "Shape_Area": 900000000.0, "gov": "GOV2", "dist": "GOV2_Y", "sd": "Y50", "Nahya_EN": "Y50" }, "geometry": { "type": "Polygon", "coordinates": [ [ [ 39.2, 36.2 ], [ 39.2, 36.4 ], [ 39.5, 36.4 ], [ 39.5, 36.2 ], [ 39.2, 36.2 ] ] ] } },
{ "type": "Feature", "properties": { "OID_": 0, "PageName": "Y51", "PageNumber": 1518, "Shape_Leng": 120000.0, "Shape_Area": 900000000.0, "gov": "GOV2", "dist": "GOV2_Y", "sd": "Y51", "Nahya_EN": "Y51" }, "geometry": { "type": "Polygon", "coordinates": [ [ [ 39.5, 36.2 ], [ 39.5, 36.4 ], [ 39.8, 36.4 ], [ 39.8, 36.2 ], [ 39.5, 36.2 ] ] ] } },
{ "type": "Feature", "properties": { "OID_": 0, "PageName": "Y52", "PageNumber": 1519, "Shape_Leng": 120000.0, "Shape_Area": 900000000.0, "gov": "GOV2", "dist": "GOV2_Y", "sd": "Y52", "Nahya_EN": "Y52" }, "geometry": { "type": "Polygon", "coordinates": [ [ [ 39.8, 36.2 ], [ 39.8, 36.4 ], [ 40.2, 36.4 ], [ 40.2, 36.2 ], [ 39.8, 36.2 ] ] ] } },
{ "type": "Feature", "properties": { "OID_": 0, "PageName": "Y53", "PageNumber": 1520, "Shape_Leng": 120000.0, "Shape_Area": 900000000.0, "gov": "GOV2", "dist": "GOV2_Y", "sd": "Y53", "Nahya_EN": "Y53" }, "geometry": { "type": "Polygon", "coordinates": [ [ [ 40.2, 36.2 ], [ 40.2, 36.4 ], [ 40.5, 36.4 ], [ 40.5, 36.2 ], [ 40.2, 36.2 ] ] ] } },
{ "type": "Feature", "properties": { "OID_": 0, "PageName": "Y54", "PageNumber": 1521, "Shape_Leng": 120000.0, "Shape_Area": 900000000.0, "gov": "GOV2", "dist": "GOV2_Y", "sd": "Y54", "Nahya_EN": "Y54" }, "geometry": { "type": "Polygon", "coordinates": [ [ [ 40.5, 36.2 ], [ 40.5, 36.4 ], [ 40.8, 36.4 ], [ 40.8, 36.2 ], [ 40.5, 36.2 ] ] ] } },
{ "type": "Feature", "properties": { "OID_": 0, "PageName": "Y55", "PageNumber": 1522, "Shape_Leng": 120000.0, "Shape_Area": 900000000.0, "gov": "GOV2", "dist": "GOV2_Y", "sd": "Y55", "Nahya_EN": "Y55" }, "geometry": { "type": "Polygon", "coordinates": [ [ [ 40.8, 36.2 ], [ 40.8, 36.4 ], [ 41.2, 36.4 ], [ 41.2, 36.2 ], [ 40.8, 36.2 ] ] ] } },
{ "type": "Feature", "properties": { "OID_": 0, "PageName": "Y56", "PageNumber": 1523, "Shape_Leng": 120000.0, "Shape_Area": 900000000.0, "gov": "GOV2", "dist": "GOV2_Y", "sd": "Y56", "Nahya_EN": "Y56" }, "geometry": { "type": "Polygon", "coordinates": [ [ [ 41.2, 36.2 ], [ 41.2, 36.4 ], [ 41.5, 36.4 ], [ 41.5, 36.1 ], [ 41.2, 36.2 ] ] ] } },
{ "type": "Feature", "properties": { "OID_": 0, "PageName": "Y57", "PageNumber": 1524, "Shape_Leng": 120000.0, "Shape_Area": 900000000.0, "gov": "GOV2", "dist": "GOV2_Y", "sd": "Y57", "Nahya_EN": "Y57" }, "geometry": { "type": "Polygon", "coordinates": [ [ [ 41.5, 36.1 ], [ 41.5, 36.4 ], [ 41.8, 36.4 ], [ 41.8, 36.1 ], [ 41.5, 36.1 ] ] ] } },
{ "type": "Feature", "properties": { "OID_": 0, "PageName": "Y58", "PageNumber": 1525, "Shape_Leng": 120000.0, "Shape_Area": 900000000.0, "gov": "GOV2", "dist": "GOV2_Y", "sd": "Y58", "Nahya_EN": "Y58" }, "geometry": { "type": "Polygon", "coordinates": [ [ [ 41.8, 36.1 ], [ 41.8, 36.4 ], [ 42.2, 36.4 ], [ 42.2, 36.1 ], [ 41.8, 36.1 ] ] ] } },
{ "type": "Feature", "properties": { "OID_": 0, "PageName": "Z40", "PageNumber": 1585, "Shape_Leng": 120000.0, "Shape_Area": 900000000.0, "gov": "GOV1", "dist": "GOV1_Z", "sd": "Z40", "Nahya_EN": "Z40" }, "geometry": { "type": "Polygon", "coordinates": [ [ [ 35.8, 35.9 ], [ 35.8, 36.1 ], [ 36.2, 36.1 ], [ 36.2, 35.9 ], [ 35.8, 35.9 ] ] ] } },
{ "type": "Feature", "properties": { "OID_": 0, "PageName": "Z41", "PageNumber": 1586, "Shape_Leng": 120000.0, "Shape_Area": 900000000.0, "gov": "GOV1", "dist": "GOV1_Z", "sd": "Z41", "Nahya_EN": "Z41" }, "geometry": { "type": "Polygon", "coordinates": [ [ [ 36.2, 35.9 ], [ 36.2, 36.1 ], [ 36.5, 36.1 ], [ 36.5, 35.9 ], [ 36.2, 35.9 ] ] ] } },
{ "type": "Feature", "properties": { "OID_": 0, "PageName": "Z42", "PageNumber": 1587, "Shape_Leng": 120000.0, "Shape_Area": 900000000.0, "gov": "GOV1", "dist": "GOV1_Z", "sd": "Z42", "Nahya_EN": "Z42" }, "geometry": { "type": "Polygon", "coordinates": [ [ [ 36.5, 35.9 ], [ 36.5, 36.1 ], [ 36.8, 36.1 ], [ 36.8, 35.9 ], [ 36.5, 35.9 ] ] ] } },
{ "type": "Feature", "properties": { "OID_": 0, "PageName": "Z43", "PageNumber": 1588, "Shape_Leng": 120000.0, "Shape_Area": 900000000.0, "gov": "GOV1", "dist": "GOV1_Z", "sd": "Z43", "Nahya_EN": "Z43" }, "geometry": { "type": "Polygon", "coordinates": [ [ [ 36.8, 35.9 ], [ 36.8, 36.1 ], [ 37.2, 36.2 ], [ 37.2, 35.9 ], [ 36.8, 35.9 ] ] ] } },
{ "type": "Feature", "properties": { "OID_": 0, "PageName": "Z44", "PageNumber": 1589, "Shape_Leng": 120000.0, "Shape_Area": 900000000.0, "gov": "GOV1", "dist": "GOV1_Z", "sd": "Z44", "Nahya_EN": "Z44" }, "geometry": { "type": "Polygon", "coordinates": [ [ [ 37.2, 35.9 ], [ 37.2, 36.2 ], [ 37.5, 36.2 ], [ 37.5, 35.9 ], [ 37.2, 35.9 ] ] ] } },
{ "type": "Feature", "properties": { "OID_": 0, "PageName": "Z45", "PageNumber": 1590, "Shape_Leng": 120000.0, "Shape_Area": 900000000.0, "gov": "GOV1", "dist": "GOV1_Z", "sd": "Z45", "Nahya_EN": "Z45" }, "geometry": { "type": "Polygon", "coordinates": [ [ [ 37.5, 35.9 ], [ 37.5, 36.2 ], [ 37.8, 36.2 ], [ 37.8, 35.9 ], [ 37.5, 35.9 ] ] ] } },
{ "type": "Feature", "properties": { "OID_": 0, "PageName": "Z46", "PageNumber": 1591, "Shape_Leng": 120000.0, "Shape_Area": 900000000.0, "gov": "GOV1", "dist": "GOV1_Z", "sd": "Z46", "Nahya_EN": "Z46" }, "geometry": { "type": "Polygon", "coordinates": [ [ [ 37.8, 35.9 ], [ 37.8, 36.2 ], [ 38.2, 36.2 ], [ 38.2, 35.9 ], [ 37.8, 35.9 ] ] ] } },
{ "type": "Feature", "properties": { "OID_": 0, "PageName": "Z47", "PageNumber": 1592, "Shape_Leng": 120000.0, "Shape_Area": 900000000.0, "gov": "GOV1", "dist": "GOV1_Z", "sd": "Z47", "Nahya_EN": "Z47" }, "geometry": { "type": "Polygon", "coordinates": [ [ [ 38.2, 35.9 ], [ 38.2, 36.2 ], [ 38.5, 36.2 ], [ 38.5, 35.9 ], [ 38.2, 35.9 ] ] ] } },
{ "type": "Feature", "properties": { "OID_": 0, "PageName": "Z48", "PageNumber": 1593, "Shape_Leng": 120000.0, "Shape_Area": 900000000.0, "gov": "GOV1", "dist": "GOV1_Z", "sd": "Z48", "Nahya_EN": "Z48" }, "geometry": { "type": "Polygon", "coordinates": [ [ [ 38.5, 35.9 ], [ 38.5, 36.2 ], [ 38.8, 36.2 ], [ 38.8, 35.9 ], [ 38.5, 35.9 ] ] ] } },
{ "type": "Feature", "properties": { "OID_": 0, "PageName": "Z49", "PageNumber": 1594, "Shape_Leng": 120000.0, "Shape_Area": 900000000.0, "gov": "GOV1", "dist": "GOV1_Z", "sd": "Z49", "Nahya_EN": "Z49" }, "geometry": { "type": "Polygon", "coordinates": [ [ [ 38.8, 35.9 ], [ 38.8, 36.2 ], [ 39.2, 36.2 ], [ 39.2, 35.9 ], [ 38.8, 35.9 ] ] ] } },
{ "type": "Feature", "properties": { "OID_": 0, "PageName": "Z50", "PageNumber": 1595, "Shape_Leng": 120000.0, "Shape_Area": 900000000.0, "gov": "GOV2", "dist": "GOV2_Z", "sd": "Z50", "Nahya_EN": "Z50" }, "geometry": { "type": "Polygon", "coordinates": [ [ [ 39.2, 35.9 ], [ 39.2, 36.2 ], [ 39.5, 36.2 ], [ 39.5, 35.9 ], [ 39.2, 35.9 ] ] ] } },
{ "type": "Feature", "properties": { "OID_": 0, "PageName": "Z51", "PageNumber": 1596, "Shape_Leng": 120000.0, "Shape_Area": 900000000.0, "gov": "GOV2", "dist": "GOV2_Z", "sd": "Z51", "Nahya_EN": "Z51" }, "geometry": { "type": "Polygon", "coordinates": [ [ [ 39.5, 35.9 ], [ 39.5, 36.2 ], [ 39.8, 36.2 ], [ 39.8, 35.9 ], [ 39.5, 35.9 ] ] ] } },
{ "type": "Feature", "properties": { "OID_": 0, "PageName": "Z52", "PageNumber": 1597, "Shape_Leng": 120000.0, "Shape_Area": 900000000.0, "gov": "GOV2", "dist": "GOV2_Z", "sd": "Z52", "Nahya_EN": "Z52" }, "geometry": { "type": "Polygon", "coordinates": [ [ [ 39.8, 35.9 ], [ 39.8, 36.2 ], [ 40.2, 36.2 ], [ 40.2, 35.9 ], [ 39.8, 35.9 ] ] ] } },
{ "type": "Feature", "properties": { "OID_": 0, "PageName": "Z53", "PageNumber": 1598, "Shape_Leng": 120000.0, "Shape_Area": 900000000.0, "gov": "GOV2", "dist": "GOV2_Z", "sd": "Z53", "Nahya_EN": "Z53" }, "geometry": { "type": "Polygon", "coordinates": [ [ [ 40.2, 35.9 ], [ 40.2, 36.2 ], [ 40.5, 36.2 ], [ 40.5, 35.9 ], [ 40.2, 35.9 ] ] ] } },
{ "type": "Feature", "properties": { "OID_": 0, "PageName": "Z54", "PageNumber": 1599, "Shape_Leng": 120000.0, "Shape_Area": 900000000.0, "gov": "GOV2", "dist": "GOV2_Z", "sd": "Z54", "Nahya_EN": "Z54" }, "geometry": { "type": "Polygon", "coordinates": [ [ [ 40.5, 35.9 ], [ 40.5, 36.2 ], [ 40.8, 36.2 ], [ 40.8, 35.9 ], [ 40.5, 35.9 ] ] ] } },
{ "type": "Feature", "properties": { "OID_": 0, "PageName": "Z55", "PageNumber": 1600, "Shape_Leng": 120000.0, "Shape_Area": 900000000.0, "gov": "GOV2", "dist": "GOV2_Z", "sd": "Z55", "Nahya_EN": "Z55" }, "geometry": { "type": "Polygon", "coordinates": [ [ [ 40.8, 35.9 ], [ 40.8, 36.2 ], [ 41.2, 36.2 ], [ 41.2, 35.9 ], [ 40.8, 35.9 ] ] ] } },
{ "type": "Feature", "properties": { "OID_": 0, "PageName": "Z56", "PageNumber": 1601, "Shape_Leng": 120000.0, "Shape_Area": 900000000.0, "gov": "GOV2", "dist": "GOV2_Z", "sd": "Z56", "Nahya_EN": "Z56" }, "geometry": { "type": "Polygon", "coordinates": [ [ [ 41.2, 35.9 ], [ 41.2, 36.2 ], [ 41.5, 36.1 ], [ 41.5, 35.9 ], [ 41.2, 35.9 ] ] ] } },
{ "type": "Feature", "properties": { "OID_": 0, "PageName": "Z57", "PageNumber": 1602, "Shape_Leng": 120000.0, "Shape_Area": 900000000.0, "gov": "GOV2", "dist": "GOV2_Z", "sd": "Z57", "Nahya_EN": "Z57" }, "geometry": { "type": "Polygon", "coordinates": [ [ [ 41.5, 35.9 ], [ 41.5, 36.1 ], [ 41.8, 36.1 ], [ 41.8, 35.9 ], [ 41.5, 35.9 ] ] ] } },
{ "type": "Feature", "properties": { "OID_": 0, "PageName": "Z58", "PageNumber": 1603, "Shape_Leng": 120000.0, "Shape_Area": 900000000.0, "gov": "GOV2", "dist": "GOV2_Z", "sd": "Z58", "Nahya_EN": "Z58" }, "geometry": { "type": "Polygon", "coordinates": [ [ [ 41.8, 35.9 ], [ 41.8, 36.1 ], [ 42.2, 36.1 ], [ 42.2, 35.9 ], [ 41.8, 35.9 ] ] ] } },
{ "type": "Feature", "properties": { "OID_": 0, "PageName": "AA40", "PageNumber": 1663, "Shape_Leng": 120000.0, "Shape_Area": 900000000.0, "gov": "GOV1", "dist": "GOV1_A", "sd": "AA40", "Nahya_EN": "AA40" }, "geometry": { "type": "Polygon", "coordinates": [ [ [ 35.8, 35.6 ], [ 35.8, 35.9 ], [ 36.2, 35.9 ], [ 36.2, 35.6 ], [ 35.8, 35.6 ] ] ] } },
{ "type": "Feature", "properties": { "OID_": 0, "PageName": "AA41", "PageNumber": 1664, "Shape_Leng": 120000.0, "Shape_Area": 900000000.0, "gov": "GOV1", "dist": "GOV1_A", "sd": "AA41", "Nahya_EN": "AA41" }, "geometry": { "type": "Polygon", "coordinates": [ [ [ 36.2, 35.6 ], [ 36.2, 35.9 ], [ 36.5, 35.9 ], [ 36.5, 35.6 ], [ 36.2, 35.6 ] ] ] } },
{ "type": "Feature", "properties": { "OID_": 0, "PageName": "AA42", "PageNumber": 1665, "Shape_Leng": 120000.0, "Shape_Area": 900000000.0, "gov": "GOV1", "dist": "GOV1_A", "sd": "AA42", "Nahya_EN": "AA42" }, "geometry": { "type": "Polygon", "coordinates": [ [ [ 36.5, 35.6 ], [ 36.5, 35.9 ], [ 36.8, 35.9 ], [ 36.8, 35.6 ], [ 36.5, 35.6 ] ] ] } },
{ "type": "Feature", "properties": { "OID_": 0, "PageName": "AA43", "PageNumber": 1666, "Shape_Leng": 120000.0, "Shape_Area": 900000000.0, "gov": "GOV1", "dist": "GOV1_A", "sd": "AA43", "Nahya_EN": "AA43" }, "geometry": { "type": "Polygon", "coordinates": [ [ [ 36.8, 35.6 ], [ 36.8, 35.9 ], [ 37.2, 35.9 ], [ 37.2, 35.6 ], [ 36.8, 35.6 ] ] ] } },
{ "type": "Feature", "properties": { "OID_": 0, "PageName": "AA44", "PageNumber": 1667, "Shape_Leng": 120000.0, "Shape_Area": 900000000.0, "gov": "GOV1", "dist": "GOV1_A", "sd": "AA44", "Nahya_EN": "AA44" }, "geometry": { "type": "Polygon", "coordinates": [ [ [ 37.2, 35.6 ], [ 37.2, 35.9 ], [ 37.5, 35.9 ], [ 37.5, 35.6 ], [ 37.2, 35.6 ] ] ] } },
{ "type": "Feature", "properties": { "OID_": 0, "PageName": "AA45", "PageNumber": 1668, "Shape_Leng": 120000.0, "Shape_Area": 900000000.0, "gov": "GOV1", "dist": "GOV1_A", "sd": "AA45", "Nahya_EN": "AA45" }, "geometry": { "type": "Polygon", "coordinates": [ [ [ 37.5, 35.6 ], [ 37.5, 35.9 ], [ 37.8, 35.9 ], [ 37.8, 35.6 ], [ 37.5, 35.6 ] ] ] } },
{ "type": "Feature", "properties": { "OID_": 0, "PageName": "AA46", "PageNumber": 1669, "Shape_Leng": 120000.0, "Shape_Area": 900000000.0, "gov": "GOV1", "dist": "GOV1_A", "sd": "AA46", "Nahya_EN": "AA46" }, "geometry": { "type": "Polygon", "coordinates": [ [ [ 37.8, 35.6 ], [ 37.8, 35.9 ], [ 38.2, 35.9 ], [ 38.2, 35.6 ], [ 37.8, 35.6 ] ] ] } },
{ "type": "Feature", "properties": { "OID_": 0, "PageName": "AA47", "PageNumber": 1670, "Shape_Leng": 120000.0, "Shape_Area": 900000000.0, "gov": "GOV1", "dist": "GOV1_A", "sd": "AA47", "Nahya_EN": "AA47" }, "geometry": { "type": "Polygon", "coordinates": [ [ [ 38.2, 35.6 ], [ 38.2, 35.9 ], [ 38.5, 35.9 ], [ 38.5, 35.6 ], [ 38.2, 35.6 ] ] ] } },
{ "type": "Feature", "properties": { "OID_": 0, "PageName": "AA48", "PageNumber": 1671, "Shape_Leng": 120000.0, "Shape_Area": 900000000.0, "gov": "GOV1", "dist": "GOV1_A", "sd": "AA48", "Nahya_EN": "AA48" }, "geometry": { "type": "Polygon", "coordinates": [ [ [ 38.5, 35.6 ], [ 38.5, 35.9 ], [ 38.8, 35.9 ], [ 38.8, 35.6 ], [ 38.5, 35.6 ] ] ] } },
{ "type": "Feature", "properties": { "OID_": 0, "PageName": "AA49", "PageNumber": 1672, "Shape_Leng": 120000.0, "Shape_Area": 900000000.0, "gov": "GOV1", "dist": "GOV1_A", "sd": "AA49", "Nahya_EN": "AA49" }, "geometry": { "type": "Polygon", "coordinates": [ [ [ 38.8, 35.6 ], [ 38.8, 35.9 ], [ 39.2, 35.9 ], [ 39.2, 35.6 ], [ 38.8, 35.6 ] ] ] } },
{ "type": "Feature", "properties": { "OID_": 0, "PageName": "AA50", "PageNumber": 1673, "Shape_Leng": 120000.0, "Shape_Area": 900000000.0, "gov": "GOV2", "dist": "GOV2_A", "sd": "AA50", "Nahya_EN": "AA50" }, "geometry": { "type": "Polygon", "coordinates": [ [ [ 39.2, 35.6 ], [ 39.2, 35.9 ], [ 39.5, 35.9 ], [ 39.5, 35.6 ], [ 39.2, 35.6 ] ] ] } },
{ "type": "Feature", "properties": { "OID_": 0, "PageName": "AA51", "PageNumber": 1674, "Shape_Leng": 120000.0, "Shape_Area": 900000000.0, "gov": "GOV2", "dist": "GOV2_A", "sd": "AA51", "Nahya_EN": "AA51" }, "geometry": { "type": "Polygon", "coordinates": [ [ [ 39.5, 35.6 ], [ 39.5, 35.9 ], [ 39.8, 35.9 ], [ 39.8, 35.6 ], [ 39.5, 35.6 ] ] ] } },
{ "type": "Feature", "properties": { "OID_": 0, "PageName": "AA52", "PageNumber": 1675, "Shape_Leng": 120000.0, "Shape_Area": 900000000.0, "gov": "GOV2", "dist": "GOV2_A", "sd": "AA52", "Nahya_EN": "AA52" }, "geometry": { "type": "Polygon", "coordinates": [ [ [ 39.8, 35.6 ], [ 39.8, 35.9 ], [ 40.2, 35.9 ], [ 40.2, 35.6 ], [ 39.8, 35.6 ] ] ] } },
{ "type": "Feature", "properties": { "OID_": 0, "PageName": "AA53", "PageNumber": 1676, "Shape_Leng": 120000.0, "Shape_Area": 900000000.0, "gov": "GOV2", "dist": "GOV2_A", "sd": "AA53", "Nahya_EN": "AA53" }, "geometry": { "type": "Polygon", "coordinates": [ [ [ 40.2, 35.6 ], [ 40.2, 35.9 ], [ 40.5, 35.9 ], [ 40.5, 35.6 ], [ 40.2, 35.6 ] ] ] } },
{ "type": "Feature", "properties": { "OID_": 0, "PageName": "AA54", "PageNumber": 1677, "Shape_Leng": 120000.0, "Shape_Area": 900000000.0, "gov": "GOV2", "dist": "GOV2_A", "sd": "AA54", "Nahya_EN": "AA54" }, "geometry": { "type": "Polygon", "coordinates": [ [ [ 40.5, 35.6 ], [ 40.5, 35.9 ], [ 40.8, 35.9 ], [ 40.8, 35.6 ], [ 40.5, 35.6 ] ] ] } },
{ "type": "Feature", "properties": { "OID_": 0, "PageName": "AA55", "PageNumber": 1678, "Shape_Leng": 120000.0, "Shape_Area": 900000000.0, "gov": "GOV2", "dist": "GOV2_A", "sd": "AA55", "Nahya_EN": "AA55" }, "geometry": { "type": "Polygon", "coordinates": [ [ [ 40.8, 35.6 ], [ 40.8, 35.9 ], [ 41.2, 35.9 ], [ 41.1, 35.6 ], [ 40.8, 35.6 ] ] ] } },
{ "type": "Feature", "properties": { "OID_": 0, "PageName": "AA56", "PageNumber": 1679, "Shape_Leng": 120000.0, "Shape_Area": 900000000.0, "gov": "GOV2", "dist": "GOV2_A", "sd": "AA56", "Nahya_EN": "AA56" }, "geometry": { "type": "Polygon", "coordinates": [ [ [ 41.1, 35.6 ], [ 41.2, 35.9 ], [ 41.5, 35.9 ], [ 41.5, 35.6 ], [ 41.1, 35.6 ] ] ] } },
{ "type": "Feature", "properties": { "OID_": 0, "PageName": "AA57", "PageNumber": 1680, "Shape_Leng": 120000.0, "Shape_Area": 900000000.0, "gov": "GOV2", "dist": "GOV2_A", "sd": "AA57", "Nahya_EN": "AA57" }, "geometry": { "type": "Polygon", "coordinates": [ [ [ 41.5, 35.6 ], [ 41.5, 35.9 ], [ 41.8, 35.9 ], [ 41.8, 35.6 ], [ 41.5, 35.6 ] ] ] } },
{ "type": "Feature", "properties": { "OID_": 0, "PageName": "AA58", "PageNumber": 1681, "Shape_Leng": 120000.0, "Shape_Area": 900000000.0, "gov": "GOV2", "dist": "GOV2_A", "sd": "AA58", "Nahya_EN": "AA58" }, "geometry": { "type": "Polygon", "coordinates": [ [ [ 41.8, 35.6 ], [ 41.8, 35.9 ], [ 42.2, 35.9 ], [ 42.1, 35.6 ], [ 41.8, 35.6 ] ] ] } },
{ "type": "Feature", "properties": { "OID_": 0, "PageName": "AB40", "PageNumber": 1741, "Shape_Leng": 120000.0, "Shape_Area": 900000000.0, "gov": "GOV1", "dist": "GOV1_A", "sd": "AB40", "Nahya_EN": "AB40" }, "geometry": { "type": "Polygon", "coordinates": [ [ [ 35.9, 35.3 ], [ 35.8, 35.6 ], [ 36.2, 35.6 ], [ 36.2, 35.3 ], [ 35.9, 35.3 ] ] ] } },
{ "type": "Feature", "properties": { "OID_": 0, "PageName": "AB41", "PageNumber": 1742, "Shape_Leng": 120000.0, "Shape_Area": 900000000.0, "gov": "GOV1", "dist": "GOV1_A", "sd": "AB41", "Nahya_EN": "AB41" }, "geometry": { "type": "Polygon", "coordinates": [ [ [ 36.2, 35.3 ], [ 36.2, 35.6 ], [ 36.5, 35.6 ], [ 36.5, 35.3 ], [ 36.2, 35.3 ] ] ] } },
{ "type": "Feature", "properties": { "OID_": 0, "PageName": "AB42", "PageNumber": 1743, "Shape_Leng": 120000.0, "Shape_Area": 900000000.0, "gov": "GOV1", "dist": "GOV1_A", "sd": "AB42", "Nahya_EN": "AB42" }, "geometry": { "type": "Polygon", "coordinates": [ [ [ 36.5, 35.3 ], [ 36.5, 35.6 ], [ 36.8, 35.6 ], [ 36.8, 35.3 ], [ 36.5, 35.3 ] ] ] } },
{ "type": "Feature", "properties": { "OID_": 0, "PageName": "AB43", "PageNumber": 1744, "Shape_Leng": 120000.0, "Shape_Area": 900000000.0, "gov": "GOV1", "dist": "GOV1_A", "sd": "AB43", "Nahya_EN": "AB43" }, "geometry": { "type": "Polygon", "coordinates": [ [ [ 36.8, 35.3 ], [ 36.8, 35.6 ], [ 37.2, 35.6 ], [ 37.2, 35.3 ], [ 36.8, 35.3 ] ] ] } },
{ "type": "Feature", "properties": { "OID_": 0, "PageName": "AB44", "PageNumber": 1745, "Shape_Leng": 120000.0, "Shape_Area": 900000000.0, "gov": "GOV1", "dist": "GOV1_A", "sd": "AB44", "Nahya_EN": "AB44" }, "geometry": { "type": "Polygon", "coordinates": [ [ [ 37.2, 35.3 ], [ 37.2, 35.6 ], [ 37.5, 35.6 ], [ 37.5, 35.3 ], [ 37.2, 35.3 ] ] ] } },
{ "type": "Feature", "properties": { "OID_": 0, "PageName": "AB45", "PageNumber": 1746, "Shape_Leng": 120000.0, "Shape_Area": 900000000.0, "gov": "GOV1", "dist": "GOV1_A", "sd": "AB45", "Nahya_EN": "AB45" }, "geometry": { "type": "Polygon", "coordinates": [ [ [ 37.5, 35.3 ], [ 37.5, 35.6 ], [ 37.8, 35.6 ], [ 37.8, 35.4 ], [ 37.5, 35.3 ] ] ] } },
{ "type": "Feature", "properties": { "OID_": 0, "PageName": "AB46", "PageNumber": 1747, "Shape_Leng": 120000.0, "Shape_Area": 900000000.0, "gov": "GOV1", "dist": "GOV1_A", "sd": "AB46", "Nahya_EN": "AB46" }, "geometry": { "type": "Polygon", "coordinates": [ [ [ 37.8, 35.4 ], [ 37.8, 35.6 ], [ 38.2, 35.6 ], [ 38.2, 35.4 ], [ 37.8, 35.4 ] ] ] } },
{ "type": "Feature", "properties": { "OID_": 0, "PageName": "AB47", "PageNumber": 1748, "Shape_Leng": 120000.0, "Shape_Area": 900000000.0, "gov": "GOV1", "dist": "GOV1_A", "sd": "AB47", "Nahya_EN": "AB47" }, "geometry": { "type": "Polygon", "coordinates": [ [ [ 38.2, 35.4 ], [ 38.2, 35.6 ], [ 38.5, 35.6 ], [ 38.5, 35.4 ], [ 38.2, 35.4 ] ] ] } },
{ "type": "Feature", "properties": { "OID_": 0, "PageName": "AB48", "PageNumber": 1749, "Shape_Leng": 120000.0, "Shape_Area": 900000000.0, "gov": "GOV1", "dist": "GOV1_A", "sd": "AB48", "Nahya_EN": "AB48" }, "geometry": { "type": "Polygon", "coordinates": [ [ [ 38.5, 35.4 ], [ 38.5, 35.6 ], [ 38.8, 35.6 ], [ 38.8, 35.4 ], [ 38.5, 35.4 ] ] ] } },
{ "type": "Feature", "properties": { "OID_": 0, "PageName": "AB49", "PageNumber": 1750, "Shape_Leng": 120000.0, "Shape_Area": 900000000.0, "gov": "GOV1", "dist": "GOV1_A", "sd": "AB49", "Nahya_EN": "AB49" }, "geometry": { "type": "Polygon", "coordinates": [ [ [ 38.8, 35.4 ], [ 38.8, 35.6 ], [ 39.2, 35.6 ], [ 39.2, 35.4 ], [ 38.8, 35.4 ] ] ] } },
{ "type": "Feature", "properties": { "OID_": 0, "PageName": "AB50", "PageNumber": 1751, "Shape_Leng": 120000.0, "Shape_Area": 900000000.0, "gov": "GOV2", "dist": "GOV2_A", "sd": "AB50", "Nahya_EN": "AB50" }, "geometry": { "type": "Polygon", "coordinates": [ [ [ 39.2, 35.4 ], [ 39.2, 35.6 ], [ 39.5, 35.6 ], [ 39.5, 35.4 ], [ 39.2, 35.4 ] ] ] } },
{ "type": "Feature", "properties": { "OID_": 0, "PageName": "AB51", "PageNumber": 1752, "Shape_Leng": 120000.0, "Shape_Area": 900000000.0, "gov": "GOV2", "dist": "GOV2_A", "sd": "AB51", "Nahya_EN": "AB51" }, "geometry": { "type": "Polygon", "coordinates": [ [ [ 39.5, 35.4 ], [ 39.5, 35.6 ], [ 39.8, 35.6 ], [ 39.8, 35.4 ], [ 39.5, 35.4 ] ] ] } },
{ "type": "Feature", "properties": { "OID_": 0, "PageName": "AB52", "PageNumber": 1753, "Shape_Leng": 120000.0, "Shape_Area": 900000000.0, "gov": "GOV2", "dist": "GOV2_A", "sd": "AB52", "Nahya_EN": "AB52" }, "geometry": { "type": "Polygon", "coordinates": [ [ [ 39.8, 35.4 ], [ 39.8, 35.6 ], [ 40.2, 35.6 ], [ 40.2, 35.4 ], [ 39.8, 35.4 ] ] ] } },
{ "type": "Feature", "properties": { "OID_": 0, "PageName": "AB53", "PageNumber": 1754, "Shape_Leng": 120000.0, "Shape_Area": 900000000.0, "gov": "GOV2", "dist": "GOV2_A", "sd": "AB53", "Nahya_EN": "AB53" }, "geometry": { "type": "Polygon", "coordinates": [ [ [ 40.2, 35.4 ], [ 40.2, 35.6 ], [ 40.5, 35.6 ], [ 40.5, 35.3 ], [ 40.2, 35.4 ] ] ] } },
{ "type": "Feature", "properties": { "OID_": 0, "PageName": "AB54", "PageNumber": 1755, "Shape_Leng": 120000.0, "Shape_Area": 900000000.0, "gov": "GOV2", "dist": "GOV2_A", "sd": "AB54", "Nahya_EN": "AB54" }, "geometry": { "type": "Polygon", "coordinates": [ [ [ 40.5, 35.3 ], [ 40.5, 35.6 ], [ 40.8, 35.6 ], [ 40.8, 35.3 ], [ 40.5, 35.3 ] ] ] } },
{ "type": "Feature", "properties": { "OID_": 0, "PageName": "AB55", "PageNumber": 1756, "Shape_Leng": 120000.0, "Shape_Area": 900000000.0, "gov": "GOV2", "dist": "GOV2_A", "sd": "AB55", "Nahya_EN": "AB55" }, "geometry": { "type": "Polygon", "coordinates": [ [ [ 40.8, 35.3 ], [ 40.8, 35.6 ], [ 41.1, 35.6 ], [ 41.1, 35.3 ], [ 40.8, 35.3 ] ] ] } },
{ "type": "Feature", "properties": { "OID_": 0, "PageName": "AB56", "PageNumber": 1757, "Shape_Leng": 120000.0, "Shape_Area": 900000000.0, "gov": "GOV2", "dist": "GOV2_A", "sd": "AB56", "Nahya_EN": "AB56" }, "geometry": { "type": "Polygon", "coordinates": [ [ [ 41.1, 35.3 ], [ 41.1, 35.6 ], [ 41.5, 35.6 ], [ 41.5, 35.3 ], [ 41.1, 35.3 ] ] ] } },
{ "type": "Feature", "properties": { "OID_": 0, "PageName": "AB57", "PageNumber": 1758, "Shape_Leng": 120000.0, "Shape_Area": 900000000.0, "gov": "GOV2", "dist": "GOV2_A", "sd": "AB57", "Nahya_EN": "AB57" }, "geometry": { "type": "Polygon", "coordinates": [ [ [ 41.5, 35.3 ], [ 41.5, 35.6 ], [ 41.8, 35.6 ], [ 41.8, 35.3 ], [ 41.5, 35.3 ] ] ] } },
{ "type": "Feature", "properties": { "OID_": 0, "PageName": "AB58", "PageNumber": 1759, "Shape_Leng": 120000.0, "Shape_Area": 900000000.0, "gov": "GOV2", "dist": "GOV2_A", "sd": "AB58", "Nahya_EN": "AB58" }, "geometry": { "type": "Polygon", "coordinates": [ [ [ 41.8, 35.3 ], [ 41.8, 35.6 ], [ 42.1, 35.6 ], [ 42.1, 35.3 ], [ 41.8, 35.3 ] ] ] } },
{ "type": "Feature", "properties": { "OID_": 0, "PageName": "AC40", "PageNumber": 1820, "Shape_Leng": 120000.0, "Shape_Area": 900000000.0, "gov": "GOV1", "dist": "GOV1_A", "sd": "AC40", "Nahya_EN": "AC40" }, "geometry": { "type": "Polygon", "coordinates": [ [ [ 35.9, 35.0 ], [ 35.9, 35.3 ], [ 36.2, 35.3 ], [ 36.2, 35.1 ], [ 35.9, 35.0 ] ] ] } },
{ "type": "Feature", "properties": { "OID_": 0, "PageName": "AC41", "PageNumber": 1821, "Shape_Leng": 120000.0, "Shape_Area": 900000000.0, "gov": "GOV1", "dist": "GOV1_A", "sd": "AC41", "Nahya_EN": "AC41" }, "geometry": { "type": "Polygon", "coordinates": [ [ [ 36.2, 35.1 ], [ 36.2, 35.3 ], [ 36.5, 35.3 ], [ 36.5, 35.1 ], [ 36.2, 35.1 ] ] ] } },
{ "type": "Feature", "properties": { "OID_": 0, "PageName": "AC42", "PageNumber": 1822, "Shape_Leng": 120000.0, "Shape_Area": 900000000.0, "gov": "GOV1", "dist": "GOV1_A", "sd": "AC42", "Nahya_EN": "AC42" }, "geometry": { "type": "Polygon", "coordinates": [ [ [ 36.5, 35.1 ], [ 36.5, 35.3 ], [ 36.8, 35.3 ], [ 36.9, 35.1 ], [ 36.5, 35.1 ] ] ] } },
{ "type": "Feature", "properties": { "OID_": 0, "PageName": "AC43", "PageNumber": 1823, "Shape_Leng": 120000.0, "Shape_Area": 900000000.0, "gov": "GOV1", "dist": "GOV1_A", "sd": "AC43", "Nahya_EN": "AC43" }, "geometry": { "type": "Polygon", "coordinates": [ [ [ 36.9, 35.1 ], [ 36.8, 35.3 ], [ 37.2, 35.3 ], [ 37.2, 35.1 ], [ 36.9, 35.1 ] ] ] } },
{ "type": "Feature", "properties": { "OID_": 0, "PageName": "AC44", "PageNumber": 1824, "Shape_Leng": 120000.0, "Shape_Area": 900000000.0, "gov": "GOV1", "dist": "GOV1_A", "sd": "AC44", "Nahya_EN": "AC44" }, "geometry": { "type": "Polygon", "coordinates": [ [ [ 37.2, 35.1 ], [ 37.2, 35.3 ], [ 37.5, 35.3 ], [ 37.5, 35.1 ], [ 37.2, 35.1 ] ] ] } },
{ "type": "Feature", "properties": { "OID_": 0, "PageName": "AC45", "PageNumber": 1825, "Shape_Leng": 120000.0, "Shape_Area": 900000000.0, "gov": "GOV1", "dist": "GOV1_A", "sd": "AC45", "Nahya_EN": "AC45" }, "geometry": { "type": "Polygon", "coordinates": [ [ [ 37.5, 35.1 ], [ 37.5, 35.3 ], [ 37.8, 35.4 ], [ 37.8, 35.1 ], [ 37.5, 35.1 ] ] ] } },
{ "type": "Feature", "properties": { "OID_": 0, "PageName": "AC46", "PageNumber": 1826, "Shape_Leng": 120000.0, "Shape_Area": 900000000.0, "gov": "GOV1", "dist": "GOV1_A", "sd": "AC46", "Nahya_EN": "AC46" }, "geometry": { "type": "Polygon", "coordinates": [ [ [ 37.8, 35.1 ], [ 37.8, 35.4 ], [ 38.2, 35.4 ], [ 38.2, 35.1 ], [ 37.8, 35.1 ] ] ] } },
{ "type": "Feature", "properties": { "OID_": 0, "PageName": "AC47", "PageNumber": 1827, "Shape_Leng": 120000.0, "Shape_Area": 900000000.0, "gov": "GOV1", "dist": "GOV1_A", "sd": "AC47", "Nahya_EN": "AC47" }, "geometry": { "type": "Polygon", "coordinates": [ [ [ 38.2, 35.1 ], [ 38.2, 35.4 ], [ 38.5, 35.4 ], [ 38.5, 35.1 ], [ 38.2, 35.1 ] ] ] } },
{ "type": "Feature", "properties": { "OID_": 0, "PageName": "AC48", "PageNumber": 1828, "Shape_Leng": 120000.0, "Shape_Area": 900000000.0, "gov": "GOV1", "dist": "GOV1_A", "sd": "AC48", "Nahya_EN": "AC48" }, "geometry": { "type": "Polygon", "coordinates": [ [ [ 38.5, 35.1 ], [ 38.5, 35.4 ], [ 38.8, 35.4 ], [ 38.8, 35.1 ], [ 38.5, 35.1 ] ] ] } },
{ "type": "Feature", "properties": { "OID_": 0, "PageName": "AC49", "PageNumber": 1829, "Shape_Leng": 120000.0, "Shape_Area": 900000000.0, "gov": "GOV1", "dist": "GOV1_A", "sd": "AC49", "Nahya_EN": "AC49" }, "geometry": { "type": "Polygon", "coordinates": [ [ [ 38.8, 35.1 ], [ 38.8, 35.4 ], [ 39.2, 35.4 ], [ 39.2, 35.1 ], [ 38.8, 35.1 ] ] ] } },
{ "type": "Feature", "properties": { "OID_": 0, "PageName": "AC50", "PageNumber": 1830, "Shape_Leng": 120000.0, "Shape_Area": 900000000.0, "gov": "GOV2", "dist": "GOV2_A", "sd": "AC50", "Nahya_EN": "AC50" }, "geometry": { "type": "Polygon", "coordinates": [ [ [ 39.2, 35.1 ], [ 39.2, 35.4 ], [ 39.5, 35.4 ], [ 39.5, 35.1 ], [ 39.2, 35.1 ] ] ] } },
{ "type": "Feature", "properties": { "OID_": 0, "PageName": "AC51", "PageNumber": 1831, "Shape_Leng": 120000.0, "Shape_Area": 900000000.0, "gov": "GOV2", "dist": "GOV2_A", "sd": "AC51", "Nahya_EN": "AC51" }, "geometry": { "type": "Polygon", "coordinates": [ [ [ 39.5, 35.1 ], [ 39.5, 35.4 ], [ 39.8, 35.4 ], [ 39.8, 35.1 ], [ 39.5, 35.1 ] ] ] } },
{ "type": "Feature", "properties": { "OID_": 0, "PageName": "AC52", "PageNumber": 1832, "Shape_Leng": 120000.0, "Shape_Area": 900000000.0, "gov": "GOV2", "dist": "GOV2_A", "sd": "AC52", "Nahya_EN": "AC52" }, "geometry": { "type": "Polygon", "coordinates": [ [ [ 39.8, 35.1 ], [ 39.8, 35.4 ], [ 40.2, 35.4 ], [ 40.1, 35.1 ], [ 39.8, 35.1 ] ] ] } },
{ "type": "Feature", "properties": { "OID_": 0, "PageName": "AC53", "PageNumber": 1833, "Shape_Leng": 120000.0, "Shape_Area": 900000000.0, "gov": "GOV2", "dist": "GOV2_A", "sd": "AC53", "Nahya_EN": "AC53" }, "geometry": { "type": "Polygon", "coordinates": [ [ [ 40.1, 35.1 ], [ 40.2, 35.4 ], [ 40.5, 35.3 ], [ 40.5, 35.1 ], [ 40.1, 35.1 ] ] ] } },
{ "type": "Feature", "properties": { "OID_": 0, "PageName": "AC54", "PageNumber": 1834, "Shape_Leng": 120000.0, "Shape_Area": 900000000.0, "gov": "GOV2", "dist": "GOV2_A", "sd": "AC54", "Nahya_EN": "AC54" }, "geometry": { "type": "Polygon", "coordinates": [ [ [ 40.5, 35.1 ], [ 40.5, 35.3 ], [ 40.8, 35.3 ], [ 40.8, 35.1 ], [ 40.5, 35.1 ] ] ] } },
{ "type": "Feature", "properties": { "OID_": 0, "PageName": "AC55", "PageNumber": 1835, "Shape_Leng": 120000.0, "Shape_Area": 900000000.0, "gov": "GOV2", "dist": "GOV2_A", "sd": "AC55", "Nahya_EN": "AC55" }, "geometry": { "type": "Polygon", "coordinates": [ [ [ 40.8, 35.1 ], [ 40.8, 35.3 ], [ 41.1, 35.3 ], [ 41.1, 35.1 ], [ 40.8, 35.1 ] ] ] } },
{ "type": "Feature", "properties": { "OID_": 0, "PageName": "AC56", "PageNumber": 1836, "Shape_Leng": 120000.0, "Shape_Area": 900000000.0, "gov": "GOV2", "dist": "GOV2_A", "sd": "AC56", "Nahya_EN": "AC56" }, "geometry": { "type": "Polygon", "coordinates": [ [ [ 41.1, 35.1 ], [ 41.1, 35.3 ], [ 41.5, 35.3 ], [ 41.5, 35.1 ], [ 41.1, 35.1 ] ] ] } },
{ "type": "Feature", "properties": { "OID_": 0, "PageName": "AC57", "PageNumber": 1837, "Shape_Leng": 120000.0, "Shape_Area": 900000000.0, "gov": "GOV2", "dist": "GOV2_A", "sd": "AC57", "Nahya_EN": "AC57" }, "geometry": { "type": "Polygon", "coordinates": [ [ [ 41.5, 35.1 ], [ 41.5, 35.3 ], [ 41.8, 35.3 ], [ 41.8, 35.1 ], [ 41.5, 35.1 ] ] ] } },
{ "type": "Feature", "properties": { "OID_": 0, "PageName": "AC58", "PageNumber": 1838, "Shape_Leng": 120000.0, "Shape_Area": 900000000.0, "gov": "GOV2", "dist": "GOV2_A", "sd": "AC58", "Nahya_EN": "AC58" }, "geometry": { "type": "Polygon", "coordinates": [ [ [ 41.8, 35.1 ], [ 41.8, 35.3 ], [ 42.1, 35.3 ], [ 42.1, 35.0 ], [ 41.8, 35.1 ] ] ] } },
{ "type": "Feature", "properties": { "OID_": 0, "PageName": "AD40", "PageNumber": 1899, "Shape_Leng": 120000.0, "Shape_Area": 900000000.0, "gov": "GOV1", "dist": "GOV1_A", "sd": "AD40", "Nahya_EN": "AD40" }, "geometry": { "type": "Polygon", "coordinates": [ [ [ 35.9, 34.8 ], [ 35.9, 35.0 ], [ 36.2, 35.1 ], [ 36.2, 34.8 ], [ 35.9, 34.8 ] ] ] } },
{ "type": "Feature", "properties": { "OID_": 0, "PageName": "AD41", "PageNumber": 1900, "Shape_Leng": 120000.0, "Shape_Area": 900000000.0, "gov": "GOV1", "dist": "GOV1_A", "sd": "AD41", "Nahya_EN": "AD41" }, "geometry": { "type": "Polygon", "coordinates": [ [ [ 36.2, 34.8 ], [ 36.2, 35.1 ], [ 36.5, 35.1 ], [ 36.5, 34.8 ], [ 36.2, 34.8 ] ] ] } },
{ "type": "Feature", "properties": { "OID_": 0, "PageName": "AD42", "PageNumber": 1901, "Shape_Leng": 120000.0, "Shape_Area": 900000000.0, "gov": "GOV1", "dist": "GOV1_A", "sd": "AD42", "Nahya_EN": "AD42" }, "geometry": { "type": "Polygon", "coordinates": [ [ [ 36.5, 34.8 ], [ 36.5, 35.1 ], [ 36.9, 35.1 ], [ 36.9, 34.8 ], [ 36.5, 34.8 ] ] ] } },
{ "type": "Feature", "properties": { "OID_": 0, "PageName": "AD43", "PageNumber": 1902, "Shape_Leng": 120000.0, "Shape_Area": 900000000.0, "gov": "GOV1", "dist": "GOV1_A", "sd": "AD43", "Nahya_EN": "AD43" }, "geometry": { "type": "Polygon", "coordinates": [ [ [ 36.9, 34.8 ], [ 36.9, 35.1 ], [ 37.2, 35.1 ], [ 37.2, 34.8 ], [ 36.9, 34.8 ] ] ] } },
{ "type": "Feature", "properties": { "OID_": 0, "PageName": "AD44", "PageNumber": 1903, "Shape_Leng": 120000.0, "Shape_Area": 900000000.0, "gov": "GOV1", "dist": "GOV1_A", "sd": "AD44", "Nahya_EN": "AD44" }, "geometry": { "type": "Polygon", "coordinates": [ [ [ 37.2, 34.8 ], [ 37.2, 35.1 ], [ 37.5, 35.1 ], [ 37.5, 34.8 ], [ 37.2, 34.8 ] ] ] } },
{ "type": "Feature", "properties": { "OID_": 0, "PageName": "AD45", "PageNumber": 1904, "Shape_Leng": 120000.0, "Shape_Area": 900000000.0, "gov": "GOV1", "dist": "GOV1_A", "sd": "AD45", "Nahya_EN": "AD45" }, "geometry": { "type": "Polygon", "coordinates": [ [ [ 37.5, 34.8 ], [ 37.5, 35.1 ], [ 37.8, 35.1 ], [ 37.8, 34.8 ], [ 37.5, 34.8 ] ] ] } },
{ "type": "Feature", "properties": { "OID_": 0, "PageName": "AD46", "PageNumber": 1905, "Shape_Leng": 120000.0, "Shape_Area": 900000000.0, "gov": "GOV1", "dist": "GOV1_A", "sd": "AD46", "Nahya_EN": "AD46" }, "geometry": { "type": "Polygon", "coordinates": [ [ [ 37.8, 34.8 ], [ 37.8, 35.1 ], [ 38.2, 35.1 ], [ 38.2, 34.8 ], [ 37.8, 34.8 ] ] ] } },
{ "type": "Feature", "properties": { "OID_": 0, "PageName": "AD47", "PageNumber": 1906, "Shape_Leng": 120000.0, "Shape_Area": 900000000.0, "gov": "GOV1", "dist": "GOV1_A", "sd": "AD47", "Nahya_EN": "AD47" }, "geometry": { "type": "Polygon", "coordinates": [ [ [ 38.2, 34.8 ], [ 38.2, 35.1 ], [ 38.5, 35.1 ], [ 38.5, 34.8 ], [ 38.2, 34.8 ] ] ] } },
{ "type": "Feature", "properties": { "OID_": 0, "PageName": "AD48", "PageNumber": 1907, "Shape_Leng": 120000.0, "Shape_Area": 900000000.0, "gov": "GOV1", "dist": "GOV1_A", "sd": "AD48", "Nahya_EN": "AD48" }, "geometry": { "type": "Polygon", "coordinates": [ [ [ 38.5, 34.8 ], [ 38.5, 35.1 ], [ 38.8, 35.1 ], [ 38.8, 34.8 ], [ 38.5, 34.8 ] ] ] } },
{ "type": "Feature", "properties": { "OID_": 0, "PageName": "AD49", "PageNumber": 1908, "Shape_Leng": 120000.0, "Shape_Area": 900000000.0, "gov": "GOV1", "dist": "GOV1_A", "sd": "AD49", "Nahya_EN": "AD49" }, "geometry": { "type": "Polygon", "coordinates": [ [ [ 38.8, 34.8 ], [ 38.8, 35.1 ], [ 39.2, 35.1 ], [ 39.2, 34.8 ], [ 38.8, 34.8 ] ] ] } },
{ "type": "Feature", "properties": { "OID_": 0, "PageName": "AD50", "PageNumber": 1909, "Shape_Leng": 120000.0, "Shape_Area": 900000000.0, "gov": "GOV2", "dist": "GOV2_A", "sd": "AD50", "Nahya_EN": "AD50" }, "geometry": { "type": "Polygon", "coordinates": [ [ [ 39.2, 34.8 ], [ 39.2, 35.1 ], [ 39.5, 35.1 ], [ 39.5, 34.8 ], [ 39.2, 34.8 ] ] ] } },
{ "type": "Feature", "properties": { "OID_": 0, "PageName": "AD51", "PageNumber": 1910, "Shape_Leng": 120000.0, "Shape_Area": 900000000.0, "gov": "GOV2", "dist": "GOV2_A", "sd": "AD51", "Nahya_EN": "AD51" }, "geometry": { "type": "Polygon", "coordinates": [ [ [ 39.5, 34.8 ], [ 39.5, 35.1 ], [ 39.8, 35.1 ], [ 39.8, 34.8 ], [ 39.5, 34.8 ] ] ] } },
{ "type": "Feature", "properties": { "OID_": 0, "PageName": "AD52", "PageNumber": 1911, "Shape_Leng": 120000.0, "Shape_Area": 900000000.0, "gov": "GOV2", "dist": "GOV2_A", "sd": "AD52", "Nahya_EN": "AD52" }, "geometry": { "type": "Polygon", "coordinates": [ [ [ 39.8, 34.8 ], [ 39.8, 35.1 ], [ 40.1, 35.1 ], [ 40.1, 34.8 ], [ 39.8, 34.8 ] ] ] } },
{ "type": "Feature", "properties": { "OID_": 0, "PageName": "AD53", "PageNumber": 1912, "Shape_Leng": 120000.0, "Shape_Area": 900000000.0, "gov": "GOV2", "dist": "GOV2_A", "sd": "AD53", "Nahya_EN": "AD53" }, "geometry": { "type": "Polygon", "coordinates": [ [ [ 40.1, 34.8 ], [ 40.1, 35.1 ], [ 40.5, 35.1 ], [ 40.5, 34.8 ], [ 40.1, 34.8 ] ] ] } },
{ "type": "Feature", "properties": { "OID_": 0, "PageName": "AD54", "PageNumber": 1913, "Shape_Leng": 120000.0, "Shape_Area": 900000000.0, "gov": "GOV2", "dist": "GOV2_A", "sd": "AD54", "Nahya_EN": "AD54" }, "geometry": { "type": "Polygon", "coordinates": [ [ [ 40.5, 34.8 ], [ 40.5, 35.1 ], [ 40.8, 35.1 ], [ 40.8, 34.8 ], [ 40.5, 34.8 ] ] ] } },
{ "type": "Feature", "properties": { "OID_": 0, "PageName": "AD55", "PageNumber": 1914, "Shape_Leng": 120000.0, "Shape_Area": 900000000.0, "gov": "GOV2", "dist": "GOV2_A", "sd": "AD55", "Nahya_EN": "AD55" }, "geometry": { "type": "Polygon", "coordinates": [ [ [ 40.8, 34.8 ], [ 40.8, 35.1 ], [ 41.1, 35.1 ], [ 41.1, 34.8 ], [ 40.8, 34.8 ] ] ] } },
{ "type": "Feature", "properties": { "OID_": 0, "PageName": "AD56", "PageNumber": 1915, "Shape_Leng": 120000.0, "Shape_Area": 900000000.0, "gov": "GOV2", "dist": "GOV2_A", "sd": "AD56", "Nahya_EN": "AD56" }, "geometry": { "type": "Polygon", "coordinates": [ [ [ 41.1, 34.8 ], [ 41.1, 35.1 ], [ 41.5, 35.1 ], [ 41.5, 34.8 ], [ 41.1, 34.8 ] ] ] } },
{ "type": "Feature", "properties": { "OID_": 0, "PageName": "AD57", "PageNumber": 1916, "Shape_Leng": 120000.0, "Shape_Area": 900000000.0, "gov": "GOV2", "dist": "GOV2_A", "sd": "AD57", "Nahya_EN": "AD57" }, "geometry": { "type": "Polygon", "coordinates": [ [ [ 41.5, 34.8 ], [ 41.5, 35.1 ], [ 41.8, 35.1 ], [ 41.8, 34.8 ], [ 41.5, 34.8 ] ] ] } },
{ "type": "Feature", "properties": { "OID_": 0, "PageName": "AD58", "PageNumber": 1917, "Shape_Leng": 120000.0, "Shape_Area": 900000000.0, "gov": "GOV2", "dist": "GOV2_A", "sd": "AD58", "Nahya_EN": "AD58" }, "geometry": { "type": "Polygon", "coordinates": [ [ [ 41.8, 34.8 ], [ 41.8, 35.1 ], [ 42.1, 35.0 ], [ 42.1, 34.8 ], [ 41.8, 34.8 ] ] ] } },
{ "type": "Feature", "properties": { "OID_": 0, "PageName": "AE40", "PageNumber": 1977, "Shape_Leng": 120000.0, "Shape_Area": 900000000.0, "gov": "GOV4", "dist": "GOV4_A", "sd": "AE40", "Nahya_EN": "AE40" }, "geometry": { "type": "Polygon", "coordinates": [ [ [ 35.9, 34.5 ], [ 35.9, 34.8 ], [ 36.2, 34.8 ], [ 36.2, 34.5 ], [ 35.9, 34.5 ] ] ] } },
{ "type": "Feature", "properties": { "OID_": 0, "PageName": "AE41", "PageNumber": 1978, "Shape_Leng": 120000.0, "Shape_Area": 900000000.0, "gov": "GOV4", "dist": "GOV4_A", "sd": "AE41", "Nahya_EN": "AE41" }, "geometry": { "type": "Polygon", "coordinates": [ [ [ 36.2, 34.5 ], [ 36.2, 34.8 ], [ 36.5, 34.8 ], [ 36.5, 34.5 ], [ 36.2, 34.5 ] ] ] } },
{ "type": "Feature", "properties": { "OID_": 0, "PageName": "AE42", "PageNumber": 1979, "Shape_Leng": 120000.0, "Shape_Area": 900000000.0, "gov": "GOV4", "dist": "GOV4_A", "sd": "AE42", "Nahya_EN": "AE42" }, "geometry": { "type": "Polygon", "coordinates": [ [ [ 36.5, 34.5 ], [ 36.5, 34.8 ], [ 36.9, 34.8 ], [ 36.9, 34.5 ], [ 36.5, 34.5 ] ] ] } },
{ "type": "Feature", "properties": { "OID_": 0, "PageName": "AE43", "PageNumber": 1980, "Shape_Leng": 120000.0, "Shape_Area": 900000000.0, "gov": "GOV4", "dist": "GOV4_A", "sd": "AE43", "Nahya_EN": "AE43" }, "geometry": { "type": "Polygon", "coordinates": [ [ [ 36.9, 34.5 ], [ 36.9, 34.8 ], [ 37.2, 34.8 ], [ 37.2, 34.5 ], [ 36.9, 34.5 ] ] ] } },
{ "type": "Feature", "properties": { "OID_": 0, "PageName": "AE44", "PageNumber": 1981, "Shape_Leng": 120000.0, "Shape_Area": 900000000.0, "gov": "GOV4", "dist": "GOV4_A", "sd": "AE44", "Nahya_EN": "AE44" }, "geometry": { "type": "Polygon", "coordinates": [ [ [ 37.2, 34.5 ], [ 37.2, 34.8 ], [ 37.5, 34.8 ], [ 37.5, 34.5 ], [ 37.2, 34.5 ] ] ] } },
{ "type": "Feature", "properties": { "OID_": 0, "PageName": "AE45", "PageNumber": 1982, "Shape_Leng": 120000.0, "Shape_Area": 900000000.0, "gov": "GOV4", "dist": "GOV4_A", "sd": "AE45", "Nahya_EN": "AE45" }, "geometry": { "type": "Polygon", "coordinates": [ [ [ 37.5, 34.5 ], [ 37.5, 34.8 ], [ 37.8, 34.8 ], [ 37.9, 34.5 ], [ 37.5, 34.5 ] ] ] } },
{ "type": "Feature", "properties": { "OID_": 0, "PageName": "AE46", "PageNumber": 1983, "Shape_Leng": 120000.0, "Shape_Area": 900000000.0, "gov": "GOV4", "dist": "GOV4_A", "sd": "AE46", "Nahya_EN": "AE46" }, "geometry": { "type": "Polygon", "coordinates": [ [ [ 37.9, 34.5 ], [ 37.8, 34.8 ], [ 38.2, 34.8 ], [ 38.2, 34.5 ], [ 37.9, 34.5 ] ] ] } },
{ "type": "Feature", "properties": { "OID_": 0, "PageName": "AE47", "PageNumber": 1984, "Shape_Leng": 120000.0, "Shape_Area": 900000000.0, "gov": "GOV4", "dist": "GOV4_A", "sd": "AE47", "Nahya_EN": "AE47" }, "geometry": { "type": "Polygon", "coordinates": [ [ [ 38.2, 34.5 ], [ 38.2, 34.8 ], [ 38.5, 34.8 ], [ 38.5, 34.5 ], [ 38.2, 34.5 ] ] ] } },
{ "type": "Feature", "properties": { "OID_": 0, "PageName": "AE48", "PageNumber": 1985, "Shape_Leng": 120000.0, "Shape_Area": 900000000.0, "gov": "GOV4", "dist": "GOV4_A", "sd": "AE48", "Nahya_EN": "AE48" }, "geometry": { "type": "Polygon", "coordinates": [ [ [ 38.5, 34.5 ], [ 38.5, 34.8 ], [ 38.8, 34.8 ], [ 38.8, 34.5 ], [ 38.5, 34.5 ] ] ] } },
{ "type": "Feature", "properties": { "OID_": 0, "PageName": "AE49", "PageNumber": 1986, "Shape_Leng": 120000.0, "Shape_Area": 900000000.0, "gov": "GOV4", "dist": "GOV4_A", "sd": "AE49", "Nahya_EN": "AE49" }, "geometry": { "type": "Polygon", "coordinates": [ [ [ 38.8, 34.5 ], [ 38.8, 34.8 ], [ 39.2, 34.8 ], [ 39.2, 34.5 ], [ 38.8, 34.5 ] ] ] } },
{ "type": "Feature", "properties": { "OID_": 0, "PageName": "AE50", "PageNumber": 1987, "Shape_Leng": 120000.0, "Shape_Area": 900000000.0, "gov": "GOV3", "dist": "GOV3_A", "sd": "AE50", "Nahya_EN": "AE50" }, "geometry": { "type": "Polygon", "coordinates": [ [ [ 39.2, 34.5 ], [ 39.2, 34.8 ], [ 39.5, 34.8 ], [ 39.5, 34.5 ], [ 39.2, 34.5 ] ] ] } },
{ "type": "Feature", "properties": { "OID_": 0, "PageName": "AE51", "PageNumber": 1988, "Shape_Leng": 120000.0, "Shape_Area": 900000000.0, "gov": "GOV3", "dist": "GOV3_A", "sd": "AE51", "Nahya_EN": "AE51" }, "geometry": { "type": "Polygon", "coordinates": [ [ [ 39.5, 34.5 ], [ 39.5, 34.8 ], [ 39.8, 34.8 ], [ 39.8, 34.5 ], [ 39.5, 34.5 ] ] ] } },
{ "type": "Feature", "properties": { "OID_": 0, "PageName": "AE52", "PageNumber": 1989, "Shape_Leng": 120000.0, "Shape_Area": 900000000.0, "gov": "GOV3", "dist": "GOV3_A", "sd": "AE52", "Nahya_EN": "AE52" }, "geometry": { "type": "Polygon", "coordinates": [ [ [ 39.8, 34.5 ], [ 39.8, 34.8 ], [ 40.1, 34.8 ], [ 40.1, 34.5 ], [ 39.8, 34.5 ] ] ] } },
{ "type": "Feature", "properties": { "OID_": 0, "PageName": "AE53", "PageNumber": 1990, "Shape_Leng": 120000.0, "Shape_Area": 900000000.0, "gov": "GOV3", "dist": "GOV3_A", "sd": "AE53", "Nahya_EN": "AE53" }, "geometry": { "type": "Polygon", "coordinates": [ [ [ 40.1, 34.5 ], [ 40.1, 34.8 ], [ 40.5, 34.8 ], [ 40.5, 34.5 ], [ 40.1, 34.5 ] ] ] } },
{ "type": "Feature", "properties": { "OID_": 0, "PageName": "AE54", "PageNumber": 1991, "Shape_Leng": 120000.0, "Shape_Area": 900000000.0, "gov": "GOV3", "dist": "GOV3_A", "sd": "AE54", "Nahya_EN": "AE54" }, "geometry": { "type": "Polygon", "coordinates": [ [ [ 40.5, 34.5 ], [ 40.5, 34.8 ], [ 40.8, 34.8 ], [ 40.8, 34.5 ], [ 40.5, 34.5 ] ] ] } },
{ "type": "Feature", "properties": { "OID_": 0, "PageName": "AE55", "PageNumber": 1992, "Shape_Leng": 120000.0, "Shape_Area": 900000000.0, "gov": "GOV3", "dist": "GOV3_A", "sd": "AE55", "Nahya_EN": "AE55" }, "geometry": { "type": "Polygon", "coordinates": [ [ [ 40.8, 34.5 ], [ 40.8, 34.8 ], [ 41.1, 34.8 ], [ 41.1, 34.5 ], [ 40.8, 34.5 ] ] ] } },
{ "type": "Feature", "properties": { "OID_": 0, "PageName": "AE56", "PageNumber": 1993, "Shape_Leng": 120000.0, "Shape_Area": 900000000.0, "gov": "GOV3", "dist": "GOV3_A", "sd": "AE56", "Nahya_EN": "AE56" }, "geometry": { "type": "Polygon", "coordinates": [ [ [ 41.1, 34.5 ], [ 41.1, 34.8 ], [ 41.5, 34.8 ], [ 41.4, 34.5 ], [ 41.1, 34.5 ] ] ] } },
{ "type": "Feature", "properties": { "OID_": 0, "PageName": "AE57", "PageNumber": 1994, "Shape_Leng": 120000.0, "Shape_Area": 900000000.0, "gov": "GOV3", "dist": "GOV3_A", "sd": "AE57", "Nahya_EN": "AE57" }, "geometry": { "type": "Polygon", "coordinates": [ [ [ 41.4, 34.5 ], [ 41.5, 34.8 ], [ 41.8, 34.8 ], [ 41.8, 34.5 ], [ 41.4, 34.5 ] ] ] } },
{ "type": "Feature", "properties": { "OID_": 0, "PageName": "AE58", "PageNumber": 1995, "Shape_Leng": 120000.0, "Shape_Area": 900000000.0, "gov": "GOV3", "dist": "GOV3_A", "sd": "AE58", "Nahya_EN": "AE58" }, "geometry": { "type": "Polygon", "coordinates": [ [ [ 41.8, 34.5 ], [ 41.8, 34.8 ], [ 42.1, 34.8 ], [ 42.1, 34.5 ], [ 41.8, 34.5 ] ] ] } },
{ "type": "Feature", "properties": { "OID_": 0, "PageName": "AF40", "PageNumber": 2057, "Shape_Leng": 120000.0, "Shape_Area": 900000000.0, "gov": "GOV4", "dist": "GOV4_A", "sd": "AF40", "Nahya_EN": "AF40" }, "geometry": { "type": "Polygon", "coordinates": [ [ [ 35.9, 34.2 ], [ 35.9, 34.5 ], [ 36.2, 34.5 ], [ 36.2, 34.2 ], [ 35.9, 34.2 ] ] ] } },
{ "type": "Feature", "properties": { "OID_": 0, "PageName": "AF41", "PageNumber": 2058, "Shape_Leng": 120000.0, "Shape_Area": 900000000.0, "gov": "GOV4", "dist": "GOV4_A", "sd": "AF41", "Nahya_EN": "AF41" }, "geometry": { "type": "Polygon", "coordinates": [ [ [ 36.2, 34.2 ], [ 36.2, 34.5 ], [ 36.5, 34.5 ], [ 36.6, 34.3 ], [ 36.2, 34.2 ] ] ] } },
{ "type": "Feature", "properties": { "OID_": 0, "PageName": "AF42", "PageNumber": 2059, "Shape_Leng": 120000.0, "Shape_Area": 900000000.0, "gov": "GOV4", "dist": "GOV4_A", "sd": "AF42", "Nahya_EN": "AF42" }, "geometry": { "type": "Polygon", "coordinates": [ [ [ 36.6, 34.3 ], [ 36.5, 34.5 ], [ 36.9, 34.5 ], [ 36.9, 34.3 ], [ 36.6, 34.3 ] ] ] } },
{ "type": "Feature", "properties": { "OID_": 0, "PageName": "AF43", "PageNumber": 2060, "Shape_Leng": 120000.0, "Shape_Area": 900000000.0, "gov": "GOV4", "dist": "GOV4_A", "sd": "AF43", "Nahya_EN": "AF43" }, "geometry": { "type": "Polygon", "coordinates": [ [ [ 36.9, 34.3 ], [ 36.9, 34.5 ], [ 37.2, 34.5 ], [ 37.2, 34.3 ], [ 36.9, 34.3 ] ] ] } },
{ "type": "Feature", "properties": { "OID_": 0, "PageName": "AF44", "PageNumber": 2061, "Shape_Leng": 120000.0, "Shape_Area": 900000000.0, "gov": "GOV4", "dist": "GOV4_A", "sd": "AF44", "Nahya_EN": "AF44" }, "geometry": { "type": "Polygon", "coordinates": [ [ [ 37.2, 34.3 ], [ 37.2, 34.5 ], [ 37.5, 34.5 ], [ 37.5, 34.3 ], [ 37.2, 34.3 ] ] ] } },
{ "type": "Feature", "properties": { "OID_": 0, "PageName": "AF45", "PageNumber": 2062, "Shape_Leng": 120000.0, "Shape_Area": 900000000.0, "gov": "GOV4", "dist": "GOV4_A", "sd": "AF45", "Nahya_EN": "AF45" }, "geometry": { "type": "Polygon", "coordinates": [ [ [ 37.5, 34.3 ], [ 37.5, 34.5 ], [ 37.9, 34.5 ], [ 37.9, 34.3 ], [ 37.5, 34.3 ] ] ] } },
{ "type": "Feature", "properties": { "OID_": 0, "PageName": "AF46", "PageNumber": 2063, "Shape_Leng": 120000.0, "Shape_Area": 900000000.0, "gov": "GOV4", "dist": "GOV4_A", "sd": "AF46", "Nahya_EN": "AF46" }, "geometry": { "type": "Polygon", "coordinates": [ [ [ 37.9, 34.3 ], [ 37.9, 34.5 ], [ 38.2, 34.5 ], [ 38.2, 34.3 ], [ 37.9, 34.3 ] ] ] } },
{ "type": "Feature", "properties": { "OID_": 0, "PageName": "AF47", "PageNumber": 2064, "Shape_Leng": 120000.0, "Shape_Area": 900000000.0, "gov": "GOV4", "dist": "GOV4_A", "sd": "AF47", "Nahya_EN": "AF47" }, "geometry": { "type": "Polygon", "coordinates": [ [ [ 38.2, 34.3 ], [ 38.2, 34.5 ], [ 38.5, 34.5 ], [ 38.5, 34.3 ], [ 38.2, 34.3 ] ] ] } },
{ "type": "Feature", "properties": { "OID_": 0, "PageName": "AF48", "PageNumber": 2065, "Shape_Leng": 120000.0, "Shape_Area": 900000000.0, "gov": "GOV4", "dist": "GOV4_A", "sd": "AF48", "Nahya_EN": "AF48" }, "geometry": { "type": "Polygon", "coordinates": [ [ [ 38.5, 34.3 ], [ 38.5, 34.5 ], [ 38.8, 34.5 ], [ 38.8, 34.3 ], [ 38.5, 34.3 ] ] ] } },
{ "type": "Feature", "properties": { "OID_": 0, "PageName": "AF49", "PageNumber": 2066, "Shape_Leng": 120000.0, "Shape_Area": 900000000.0, "gov": "GOV4", "dist": "GOV4_A", "sd": "AF49", "Nahya_EN": "AF49" }, "geometry": { "type": "Polygon", "coordinates": [ [ [ 38.8, 34.3 ], [ 38.8, 34.5 ], [ 39.2, 34.5 ], [ 39.2, 34.3 ], [ 38.8, 34.3 ] ] ] } },
{ "type": "Feature", "properties": { "OID_": 0, "PageName": "AF50", "PageNumber": 2067, "Shape_Leng": 120000.0, "Shape_Area": 900000000.0, "gov": "GOV3", "dist": "GOV3_A", "sd": "AF50", "Nahya_EN": "AF50" }, "geometry": { "type": "Polygon", "coordinates": [ [ [ 39.2, 34.3 ], [ 39.2, 34.5 ], [ 39.5, 34.5 ], [ 39.5, 34.3 ], [ 39.2, 34.3 ] ] ] } },
{ "type": "Feature", "properties": { "OID_": 0, "PageName": "AF51", "PageNumber": 2068, "Shape_Leng": 120000.0, "Shape_Area": 900000000.0, "gov": "GOV3", "dist": "GOV3_A", "sd": "AF51", "Nahya_EN": "AF51" }, "geometry": { "type": "Polygon", "coordinates": [ [ [ 39.5, 34.3 ], [ 39.5, 34.5 ], [ 39.8, 34.5 ], [ 39.8, 34.3 ], [ 39.5, 34.3 ] ] ] } },
{ "type": "Feature", "properties": { "OID_": 0, "PageName": "AF52", "PageNumber": 2069, "Shape_Leng": 120000.0, "Shape_Area": 900000000.0, "gov": "GOV3", "dist": "GOV3_A", "sd": "AF52", "Nahya_EN": "AF52" }, "geometry": { "type": "Polygon", "coordinates": [ [ [ 39.8, 34.3 ], [ 39.8, 34.5 ], [ 40.1, 34.5 ], [ 40.1, 34.3 ], [ 39.8, 34.3 ] ] ] } },
{ "type": "Feature", "properties": { "OID_": 0, "PageName": "AF53", "PageNumber": 2070, "Shape_Leng": 120000.0, "Shape_Area": 900000000.0, "gov": "GOV3", "dist": "GOV3_A", "sd": "AF53", "Nahya_EN": "AF53" }, "geometry": { "type": "Polygon", "coordinates": [ [ [ 40.1, 34.3 ], [ 40.1, 34.5 ], [ 40.5, 34.5 ], [ 40.5, 34.3 ], [ 40.1, 34.3 ] ] ] } },
{ "type": "Feature", "properties": { "OID_": 0, "PageName": "AF54", "PageNumber": 2071, "Shape_Leng": 120000.0, "Shape_Area": 900000000.0, "gov": "GOV3", "dist": "GOV3_A", "sd": "AF54", "Nahya_EN": "AF54" }, "geometry": { "type": "Polygon", "coordinates": [ [ [ 40.5, 34.3 ], [ 40.5, 34.5 ], [ 40.8, 34.5 ], [ 40.8, 34.3 ], [ 40.5, 34.3 ] ] ] } },
{ "type": "Feature", "properties": { "OID_": 0, "PageName": "AF55", "PageNumber": 2072, "Shape_Leng": 120000.0, "Shape_Area": 900000000.0, "gov": "GOV3", "dist": "GOV3_A", "sd": "AF55", "Nahya_EN": "AF55" }, "geometry": { "type": "Polygon", "coordinates": [ [ [ 40.8, 34.3 ], [ 40.8, 34.5 ], [ 41.1, 34.5 ], [ 41.1, 34.3 ], [ 40.8, 34.3 ] ] ] } },
{ "type": "Feature", "properties": { "OID_": 0, "PageName": "AF56", "PageNumber": 2073, "Shape_Leng": 120000.0, "Shape_Area": 900000000.0, "gov": "GOV3", "dist": "GOV3_A", "sd": "AF56", "Nahya_EN": "AF56" }, "geometry": { "type": "Polygon", "coordinates": [ [ [ 41.1, 34.3 ], [ 41.1, 34.5 ], [ 41.4, 34.5 ], [ 41.4, 34.3 ], [ 41.1, 34.3 ] ] ] } },
{ "type": "Feature", "properties": { "OID_": 0, "PageName": "AF57", "PageNumber": 2074, "Shape_Leng": 120000.0, "Shape_Area": 900000000.0, "gov": "GOV3", "dist": "GOV3_A", "sd": "AF57", "Nahya_EN": "AF57" }, "geometry": { "type": "Polygon", "coordinates": [ [ [ 41.4, 34.3 ], [ 41.4, 34.5 ], [ 41.8, 34.5 ], [ 41.8, 34.2 ], [ 41.4, 34.3 ] ] ] } },
{ "type": "Feature", "properties": { "OID_": 0, "PageName": "AF58", "PageNumber": 2075, "Shape_Leng": 120000.0, "Shape_Area": 900000000.0, "gov": "GOV3", "dist": "GOV3_A", "sd": "AF58", "Nahya_EN": "AF58" }, "geometry": { "type": "Polygon", "coordinates": [ [ [ 41.8, 34.2 ], [ 41.8, 34.5 ], [ 42.1, 34.5 ], [ 42.1, 34.2 ], [ 41.8, 34.2 ] ] ] } },
{ "type": "Feature", "properties": { "OID_": 0, "PageName": "AG40", "PageNumber": 2137, "Shape_Leng": 120000.0, "Shape_Area": 900000000.0, "gov": "GOV4", "dist": "GOV4_A", "sd": "AG40", "Nahya_EN": "AG40" }, "geometry": { "type": "Polygon", "coordinates": [ [ [ 35.9, 34.0 ], [ 35.9, 34.2 ], [ 36.2, 34.2 ], [ 36.2, 34.0 ], [ 35.9, 34.0 ] ] ] } },
{ "type": "Feature", "properties": { "OID_": 0, "PageName": "AG41", "PageNumber": 2138, "Shape_Leng": 120000.0, "Shape_Area": 900000000.0, "gov": "GOV4", "dist": "GOV4_A", "sd": "AG41", "Nahya_EN": "AG41" }, "geometry": { "type": "Polygon", "coordinates": [ [ [ 36.2, 34.0 ], [ 36.2, 34.2 ], [ 36.6, 34.3 ], [ 36.6, 34.0 ], [ 36.2, 34.0 ] ] ] } },
{ "type": "Feature", "properties": { "OID_": 0, "PageName": "AG42", "PageNumber": 2139, "Shape_Leng": 120000.0, "Shape_Area": 900000000.0, "gov": "GOV4", "dist": "GOV4_A", "sd": "AG42", "Nahya_EN": "AG42" }, "geometry": { "type": "Polygon", "coordinates": [ [ [ 36.6, 34.0 ], [ 36.6, 34.3 ], [ 36.9, 34.3 ], [ 36.9, 34.0 ], [ 36.6, 34.0 ] ] ] } },
{ "type": "Feature", "properties": { "OID_": 0, "PageName": "AG43", "PageNumber": 2140, "Shape_Leng": 120000.0, "Shape_Area": 900000000.0, "gov": "GOV4", "dist": "GOV4_A", "sd": "AG43", "Nahya_EN": "AG43" }, "geometry": { "type": "Polygon", "coordinates": [ [ [ 36.9, 34.0 ], [ 36.9, 34.3 ], [ 37.2, 34.3 ], [ 37.2, 34.0 ], [ 36.9, 34.0 ] ] ] } },
{ "type": "Feature", "properties": { "OID_": 0, "PageName": "AG44", "PageNumber": 2141, "Shape_Leng": 120000.0, "Shape_Area": 900000000.0, "gov": "GOV4", "dist": "GOV4_A", "sd": "AG44", "Nahya_EN": "AG44" }, "geometry": { "type": "Polygon", "coordinates": [ [ [ 37.2, 34.0 ], [ 37.2, 34.3 ], [ 37.5, 34.3 ], [ 37.5, 34.0 ], [ 37.2, 34.0 ] ] ] } },
{ "type": "Feature", "properties": { "OID_": 0, "PageName": "AG45", "PageNumber": 2142, "Shape_Leng": 120000.0, "Shape_Area": 900000000.0, "gov": "GOV4", "dist": "GOV4_A", "sd": "AG45", "Nahya_EN": "AG45" }, "geometry": { "type": "Polygon", "coordinates": [ [ [ 37.5, 34.0 ], [ 37.5, 34.3 ], [ 37.9, 34.3 ], [ 37.9, 34.0 ], [ 37.5, 34.0 ] ] ] } },
{ "type": "Feature", "properties": { "OID_": 0, "PageName": "AG46", "PageNumber": 2143, "Shape_Leng": 120000.0, "Shape_Area": 900000000.0, "gov": "GOV4", "dist": "GOV4_A", "sd": "AG46", "Nahya_EN": "AG46" }, "geometry": { "type": "Polygon", "coordinates": [ [ [ 37.9, 34.0 ], [ 37.9, 34.3 ], [ 38.2, 34.3 ], [ 38.2, 34.0 ], [ 37.9, 34.0 ] ] ] } },
{ "type": "Feature", "properties": { "OID_": 0, "PageName": "AG47", "PageNumber": 2144, "Shape_Leng": 120000.0, "Shape_Area": 900000000.0, "gov": "GOV4", "dist": "GOV4_A", "sd": "AG47", "Nahya_EN": "AG47" }, "geometry": { "type": "Polygon", "coordinates": [ [ [ 38.2, 34.0 ], [ 38.2, 34.3 ], [ 38.5, 34.3 ], [ 38.5, 34.0 ], [ 38.2, 34.0 ] ] ] } },
{ "type": "Feature", "properties": { "OID_": 0, "PageName": "AG48", "PageNumber": 2145, "Shape_Leng": 120000.0, "Shape_Area": 900000000.0, "gov": "GOV4", "dist": "GOV4_A", "sd": "AG48", "Nahya_EN": "AG48" }, "geometry": { "type": "Polygon", "coordinates": [ [ [ 38.5, 34.0 ], [ 38.5, 34.3 ], [ 38.8, 34.3 ], [ 38.8, 34.0 ], [ 38.5, 34.0 ] ] ] } },
{ "type": "Feature", "properties": { "OID_": 0, "PageName": "AG49", "PageNumber": 2146, "Shape_Leng": 120000.0, "Shape_Area": 900000000.0, "gov": "GOV4", "dist": "GOV4_A", "sd": "AG49", "Nahya_EN": "AG49" }, "geometry": { "type": "Polygon", "coordinates": [ [ [ 38.8, 34.0 ], [ 38.8, 34.3 ], [ 39.2, 34.3 ], [ 39.2, 34.0 ], [ 38.8, 34.0 ] ] ] } },
{ "type": "Feature", "properties": { "OID_": 0, "PageName": "AG50", "PageNumber": 2147, "Shape_Leng": 120000.0, "Shape_Area": 900000000.0, "gov": "GOV3", "dist": "GOV3_A", "sd": "AG50", "Nahya_EN": "AG50" }, "geometry": { "type": "Polygon", "coordinates": [ [ [ 39.2, 34.0 ], [ 39.2, 34.3 ], [ 39.5, 34.3 ], [ 39.5, 34.0 ], [ 39.2, 34.0 ] ] ] } },
{ "type": "Feature", "properties": { "OID_": 0, "PageName": "AG51", "PageNumber": 2148, "Shape_Leng": 120000.0, "Shape_Area": 900000000.0, "gov": "GOV3", "dist": "GOV3_A", "sd": "AG51", "Nahya_EN": "AG51" }, "geometry": { "type": "Polygon", "coordinates": [ [ [ 39.5, 34.0 ], [ 39.5, 34.3 ], [ 39.8, 34.3 ], [ 39.8, 34.0 ], [ 39.5, 34.0 ] ] ] } },
{ "type": "Feature", "properties": { "OID_": 0, "PageName": "AG52", "PageNumber": 2149, "Shape_Leng": 120000.0, "Shape_Area": 900000000.0, "gov": "GOV3", "dist": "GOV3_A", "sd": "AG52", "Nahya_EN": "AG52" }, "geometry": { "type": "Polygon", "coordinates": [ [ [ 39.8, 34.0 ], [ 39.8, 34.3 ], [ 40.1, 34.3 ], [ 40.1, 34.0 ], [ 39.8, 34.0 ] ] ] } },
{ "type": "Feature", "properties": { "OID_": 0, "PageName": "AG53", "PageNumber": 2150, "Shape_Leng": 120000.0, "Shape_Area": 900000000.0, "gov": "GOV3", "dist": "GOV3_A", "sd": "AG53", "Nahya_EN": "AG53" }, "geometry": { "type": "Polygon", "coordinates": [ [ [ 40.1, 34.0 ], [ 40.1, 34.3 ], [ 40.5, 34.3 ], [ 40.5, 34.0 ], [ 40.1, 34.0 ] ] ] } },
{ "type": "Feature", "properties": { "OID_": 0, "PageName": "AG54", "PageNumber": 2151, "Shape_Leng": 120000.0, "Shape_Area": 900000000.0, "gov": "GOV3", "dist": "GOV3_A", "sd": "AG54", "Nahya_EN": "AG54" }, "geometry": { "type": "Polygon", "coordinates": [ [ [ 40.5, 34.0 ], [ 40.5, 34.3 ], [ 40.8, 34.3 ], [ 40.8, 34.0 ], [ 40.5, 34.0 ] ] ] } },
{ "type": "Feature", "properties": { "OID_": 0, "PageName": "AG55", "PageNumber": 2152, "Shape_Leng": 120000.0, "Shape_Area": 900000000.0, "gov": "GOV3", "dist": "GOV3_A", "sd": "AG55", "Nahya_EN": "AG55" }, "geometry": { "type": "Polygon", "coordinates": [ [ [ 40.8, 34.0 ], [ 40.8, 34.3 ], [ 41.1, 34.3 ], [ 41.1, 34.0 ], [ 40.8, 34.0 ] ] ] } },
{ "type": "Feature", "properties": { "OID_": 0, "PageName": "AG56", "PageNumber": 2153, "Shape_Leng": 120000.0, "Shape_Area": 900000000.0, "gov": "GOV3", "dist": "GOV3_A", "sd": "AG56", "Nahya_EN": "AG56" }, "geometry": { "type": "Polygon", "coordinates": [ [ [ 41.1, 34.0 ], [ 41.1, 34.3 ], [ 41.4, 34.3 ], [ 41.4, 34.0 ], [ 41.1, 34.0 ] ] ] } },
{ "type": "Feature", "properties": { "OID_": 0, "PageName": "AG57", "PageNumber": 2154, "Shape_Leng": 120000.0, "Shape_Area": 900000000.0, "gov": "GOV3", "dist": "GOV3_A", "sd": "AG57", "Nahya_EN": "AG57" }, "geometry": { "type": "Polygon", "coordinates": [ [ [ 41.4, 34.0 ], [ 41.4, 34.3 ], [ 41.8, 34.2 ], [ 41.8, 34.0 ], [ 41.4, 34.0 ] ] ] } },
{ "type": "Feature", "properties": { "OID_": 0, "PageName": "AG58", "PageNumber": 2155, "Shape_Leng": 120000.0, "Shape_Area": 900000000.0, "gov": "GOV3", "dist": "GOV3_A", "sd": "AG58", "Nahya_EN": "AG58" }, "geometry": { "type": "Polygon", "coordinates": [ [ [ 41.8, 34.0 ], [ 41.8, 34.2 ], [ 42.1, 34.2 ], [ 42.1, 34.0 ], [ 41.8, 34.0 ] ] ] } },
{ "type": "Feature", "properties": { "OID_": 0, "PageName": "AH40", "PageNumber": 2218, "Shape_Leng": 120000.0, "Shape_Area": 900000000.0, "gov": "GOV4", "dist": "GOV4_A", "sd": "AH40", "Nahya_EN": "AH40" }, "geometry": { "type": "Polygon", "coordinates": [ [ [ 35.9, 33.7 ], [ 35.9, 34.0 ], [ 36.2, 34.0 ], [ 36.2, 33.7 ], [ 35.9, 33.7 ] ] ] } },
{ "type": "Feature", "properties": { "OID_": 0, "PageName": "AH41", "PageNumber": 2219, "Shape_Leng": 120000.0, "Shape_Area": 900000000.0, "gov": "GOV4", "dist": "GOV4_A", "sd": "AH41", "Nahya_EN": "AH41" }, "geometry": { "type": "Polygon", "coordinates": [ [ [ 36.2, 33.7 ], [ 36.2, 34.0 ], [ 36.6, 34.0 ], [ 36.6, 33.7 ], [ 36.2, 33.7 ] ] ] } },
{ "type": "Feature", "properties": { "OID_": 0, "PageName": "AH42", "PageNumber": 2220, "Shape_Leng": 120000.0, "Shape_Area": 900000000.0, "gov": "GOV4", "dist": "GOV4_A", "sd": "AH42", "Nahya_EN": "AH42" }, "geometry": { "type": "Polygon", "coordinates": [ [ [ 36.6, 33.7 ], [ 36.6, 34.0 ], [ 36.9, 34.0 ], [ 36.9, 33.7 ], [ 36.6, 33.7 ] ] ] } },
{ "type": "Feature", "properties": { "OID_": 0, "PageName": "AH43", "PageNumber": 2221, "Shape_Leng": 120000.0, "Shape_Area": 900000000.0, "gov": "GOV4", "dist": "GOV4_A", "sd": "AH43", "Nahya_EN": "AH43" }, "geometry": { "type": "Polygon", "coordinates": [ [ [ 36.9, 33.7 ], [ 36.9, 34.0 ], [ 37.2, 34.0 ], [ 37.2, 33.7 ], [ 36.9, 33.7 ] ] ] } },
{ "type": "Feature", "properties": { "OID_": 0, "PageName": "AH44", "PageNumber": 2222, "Shape_Leng": 120000.0, "Shape_Area": 900000000.0, "gov": "GOV4", "dist": "GOV4_A", "sd": "AH44", "Nahya_EN": "AH44" }, "geometry": { "type": "Polygon", "coordinates": [ [ [ 37.2, 33.7 ], [ 37.2, 34.0 ], [ 37.5, 34.0 ], [ 37.5, 33.7 ], [ 37.2, 33.7 ] ] ] } },
{ "type": "Feature", "properties": { "OID_": 0, "PageName": "AH45", "PageNumber": 2223, "Shape_Leng": 120000.0, "Shape_Area": 900000000.0, "gov": "GOV4", "dist": "GOV4_A", "sd": "AH45", "Nahya_EN": "AH45" }, "geometry": { "type": "Polygon", "coordinates": [ [ [ 37.5, 33.7 ], [ 37.5, 34.0 ], [ 37.9, 34.0 ], [ 37.9, 33.7 ], [ 37.5, 33.7 ] ] ] } },
{ "type": "Feature", "properties": { "OID_": 0, "PageName": "AH46", "PageNumber": 2224, "Shape_Leng": 120000.0, "Shape_Area": 900000000.0, "gov": "GOV4", "dist": "GOV4_A", "sd": "AH46", "Nahya_EN": "AH46" }, "geometry": { "type": "Polygon", "coordinates": [ [ [ 37.9, 33.7 ], [ 37.9, 34.0 ], [ 38.2, 34.0 ], [ 38.2, 33.7 ], [ 37.9, 33.7 ] ] ] } },
{ "type": "Feature", "properties": { "OID_": 0, "PageName": "AH47", "PageNumber": 2225, "Shape_Leng": 120000.0, "Shape_Area": 900000000.0, "gov": "GOV4", "dist": "GOV4_A", "sd": "AH47", "Nahya_EN": "AH47" }, "geometry": { "type": "Polygon", "coordinates": [ [ [ 38.2, 33.7 ], [ 38.2, 34.0 ], [ 38.5, 34.0 ], [ 38.5, 33.7 ], [ 38.2, 33.7 ] ] ] } },
{ "type": "Feature", "properties": { "OID_": 0, "PageName": "AH48", "PageNumber": 2226, "Shape_Leng": 120000.0, "Shape_Area": 900000000.0, "gov": "GOV4", "dist": "GOV4_A", "sd": "AH48", "Nahya_EN": "AH48" }, "geometry": { "type": "Polygon", "coordinates": [ [ [ 38.5, 33.7 ], [ 38.5, 34.0 ], [ 38.8, 34.0 ], [ 38.8, 33.7 ], [ 38.5, 33.7 ] ] ] } },
{ "type": "Feature", "properties": { "OID_": 0, "PageName": "AH49", "PageNumber": 2227, "Shape_Leng": 120000.0, "Shape_Area": 900000000.0, "gov": "GOV4", "dist": "GOV4_A", "sd": "AH49", "Nahya_EN": "AH49" }, "geometry": { "type": "Polygon", "coordinates": [ [ [ 38.8, 33.7 ], [ 38.8, 34.0 ], [ 39.2, 34.0 ], [ 39.2, 33.7 ], [ 38.8, 33.7 ] ] ] } },
{ "type": "Feature", "properties": { "OID_": 0, "PageName": "AH50", "PageNumber": 2228, "Shape_Leng": 120000.0, "Shape_Area": 900000000.0, "gov": "GOV3", "dist": "GOV3_A", "sd": "AH50", "Nahya_EN": "AH50" }, "geometry": { "type": "Polygon", "coordinates": [ [ [ 39.2, 33.7 ], [ 39.2, 34.0 ], [ 39.5, 34.0 ], [ 39.5, 33.7 ], [ 39.2, 33.7 ] ] ] } },
{ "type": "Feature", "properties": { "OID_": 0, "PageName": "AH51", "PageNumber": 2229, "Shape_Leng": 120000.0, "Shape_Area": 900000000.0, "gov": "GOV3", "dist": "GOV3_A", "sd": "AH51", "Nahya_EN": "AH51" }, "geometry": { "type": "Polygon", "coordinates": [ [ [ 39.5, 33.7 ], [ 39.5, 34.0 ], [ 39.8, 34.0 ], [ 39.8, 33.7 ], [ 39.5, 33.7 ] ] ] } },
{ "type": "Feature", "properties": { "OID_": 0, "PageName": "AH52", "PageNumber": 2230, "Shape_Leng": 120000.0, "Shape_Area": 900000000.0, "gov": "GOV3", "dist": "GOV3_A", "sd": "AH52", "Nahya_EN": "AH52" }, "geometry": { "type": "Polygon", "coordinates": [ [ [ 39.8, 33.7 ], [ 39.8, 34.0 ], [ 40.1, 34.0 ], [ 40.1, 33.7 ], [ 39.8, 33.7 ] ] ] } },
{ "type": "Feature", "properties": { "OID_": 0, "PageName": "AH53", "PageNumber": 2231, "Shape_Leng": 120000.0, "Shape_Area": 900000000.0, "gov": "GOV3", "dist": "GOV3_A", "sd": "AH53", "Nahya_EN": "AH53" }, "geometry": { "type": "Polygon", "coordinates": [ [ [ 40.1, 33.7 ], [ 40.1, 34.0 ], [ 40.5, 34.0 ], [ 40.5, 33.7 ], [ 40.1, 33.7 ] ] ] } },
{ "type": "Feature", "properties": { "OID_": 0, "PageName": "AH54", "PageNumber": 2232, "Shape_Leng": 120000.0, "Shape_Area": 900000000.0, "gov": "GOV3", "dist": "GOV3_A", "sd": "AH54", "Nahya_EN": "AH54" }, "geometry": { "type": "Polygon", "coordinates": [ [ [ 40.5, 33.7 ], [ 40.5, 34.0 ], [ 40.8, 34.0 ], [ 40.8, 33.7 ], [ 40.5, 33.7 ] ] ] } },
{ "type": "Feature", "properties": { "OID_": 0, "PageName": "AH55", "PageNumber": 2233, "Shape_Leng": 120000.0, "Shape_Area": 900000000.0, "gov": "GOV3", "dist": "GOV3_A", "sd": "AH55", "Nahya_EN": "AH55" }, "geometry": { "type": "Polygon", "coordinates": [ [ [ 40.8, 33.7 ], [ 40.8, 34.0 ], [ 41.1, 34.0 ], [ 41.1, 33.7 ], [ 40.8, 33.7 ] ] ] } },
{ "type": "Feature", "properties": { "OID_": 0, "PageName": "AH56", "PageNumber": 2234, "Shape_Leng": 120000.0, "Shape_Area": 900000000.0, "gov": "GOV3", "dist": "GOV3_A", "sd": "AH56", "Nahya_EN": "AH56" }, "geometry": { "type": "Polygon", "coordinates": [ [ [ 41.1, 33.7 ], [ 41.1, 34.0 ], [ 41.4, 34.0 ], [ 41.4, 33.7 ], [ 41.1, 33.7 ] ] ] } },
{ "type": "Feature", "properties": { "OID_": 0, "PageName": "AH57", "PageNumber": 2235, "Shape_Leng": 120000.0, "Shape_Area": 900000000.0, "gov": "GOV3", "dist": "GOV3_A", "sd": "AH57", "Nahya_EN": "AH57" }, "geometry": { "type": "Polygon", "coordinates": [ [ [ 41.4, 33.7 ], [ 41.4, 34.0 ], [ 41.8, 34.0 ], [ 41.7, 33.7 ], [ 41.4, 33.7 ] ] ] } },
{ "type": "Feature", "properties": { "OID_": 0, "PageName": "AH58", "PageNumber": 2236, "Shape_Leng": 120000.0, "Shape_Area": 900000000.0, "gov": "GOV3", "dist": "GOV3_A", "sd": "AH58", "Nahya_EN": "AH58" }, "geometry": { "type": "Polygon", "coordinates": [ [ [ 41.7, 33.7 ], [ 41.8, 34.0 ], [ 42.1, 34.0 ], [ 42.1, 33.7 ], [ 41.7, 33.7 ] ] ] } },
{ "type": "Feature", "properties": { "OID_": 0, "PageName": "AI40", "PageNumber": 2300, "Shape_Leng": 120000.0, "Shape_Area": 900000000.0, "gov": "GOV4", "dist": "GOV4_A", "sd": "AI40", "Nahya_EN": "AI40" }, "geometry": { "type": "Polygon", "coordinates": [ [ [ 35.9, 33.4 ], [ 35.9, 33.7 ], [ 36.2, 33.7 ], [ 36.3, 33.4 ], [ 35.9, 33.4 ] ] ] } },
{ "type": "Feature", "properties": { "OID_": 0, "PageName": "AI41", "PageNumber": 2301, "Shape_Leng": 120000.0, "Shape_Area": 900000000.0, "gov": "GOV4", "dist": "GOV4_A", "sd": "AI41", "Nahya_EN": "AI41" }, "geometry": { "type": "Polygon", "coordinates": [ [ [ 36.3, 33.4 ], [ 36.2, 33.7 ], [ 36.6, 33.7 ], [ 36.6, 33.4 ], [ 36.3, 33.4 ] ] ] } },
{ "type": "Feature", "properties": { "OID_": 0, "PageName": "AI42", "PageNumber": 2302, "Shape_Leng": 120000.0, "Shape_Area": 900000000.0, "gov": "GOV4", "dist": "GOV4_A", "sd": "AI42", "Nahya_EN": "AI42" }, "geometry": { "type": "Polygon", "coordinates": [ [ [ 36.6, 33.4 ], [ 36.6, 33.7 ], [ 36.9, 33.7 ], [ 36.9, 33.4 ], [ 36.6, 33.4 ] ] ] } },
{ "type": "Feature", "properties": { "OID_": 0, "PageName": "AI43", "PageNumber": 2303, "Shape_Leng": 120000.0, "Shape_Area": 900000000.0, "gov": "GOV4", "dist": "GOV4_A", "sd": "AI43", "Nahya_EN": "AI43" }, "geometry": { "type": "Polygon", "coordinates": [ [ [ 36.9, 33.4 ], [ 36.9, 33.7 ], [ 37.2, 33.7 ], [ 37.2, 33.5 ], [ 36.9, 33.4 ] ] ] } },
{ "type": "Feature", "properties": { "OID_": 0, "PageName": "AI44", "PageNumber": 2304, "Shape_Leng": 120000.0, "Shape_Area": 900000000.0, "gov": "GOV4", "dist": "GOV4_A", "sd": "AI44", "Nahya_EN": "AI44" }, "geometry": { "type": "Polygon", "coordinates": [ [ [ 37.2, 33.5 ], [ 37.2, 33.7 ], [ 37.5, 33.7 ], [ 37.5, 33.5 ], [ 37.2, 33.5 ] ] ] } },
{ "type": "Feature", "properties": { "OID_": 0, "PageName": "AI45", "PageNumber": 2305, "Shape_Leng": 120000.0, "Shape_Area": 900000000.0, "gov": "GOV4", "dist": "GOV4_A", "sd": "AI45", "Nahya_EN": "AI45" }, "geometry": { "type": "Polygon", "coordinates": [ [ [ 37.5, 33.5 ], [ 37.5, 33.7 ], [ 37.9, 33.7 ], [ 37.9, 33.5 ], [ 37.5, 33.5 ] ] ] } },
{ "type": "Feature", "properties": { "OID_": 0, "PageName": "AI46", "PageNumber": 2306, "Shape_Leng": 120000.0, "Shape_Area": 900000000.0, "gov": "GOV4", "dist": "GOV4_A", "sd": "AI46", "Nahya_EN": "AI46" }, "geometry": { "type": "Polygon", "coordinates": [ [ [ 37.9, 33.5 ], [ 37.9, 33.7 ], [ 38.2, 33.7 ], [ 38.2, 33.5 ], [ 37.9, 33.5 ] ] ] } },
{ "type": "Feature", "properties": { "OID_": 0, "PageName": "AI47", "PageNumber": 2307, "Shape_Leng": 120000.0, "Shape_Area": 900000000.0, "gov": "GOV4", "dist": "GOV4_A", "sd": "AI47", "Nahya_EN": "AI47" }, "geometry": { "type": "Polygon", "coordinates": [ [ [ 38.2, 33.5 ], [ 38.2, 33.7 ], [ 38.5, 33.7 ], [ 38.5, 33.5 ], [ 38.2, 33.5 ] ] ] } },
{ "type": "Feature", "properties": { "OID_": 0, "PageName": "AI48", "PageNumber": 2308, "Shape_Leng": 120000.0, "Shape_Area": 900000000.0, "gov": "GOV4", "dist": "GOV4_A", "sd": "AI48", "Nahya_EN": "AI48" }, "geometry": { "type": "Polygon", "coordinates": [ [ [ 38.5, 33.5 ], [ 38.5, 33.7 ], [ 38.8, 33.7 ], [ 38.8, 33.5 ], [ 38.5, 33.5 ] ] ] } },
{ "type": "Feature", "properties": { "OID_": 0, "PageName": "AI49", "PageNumber": 2309, "Shape_Leng": 120000.0, "Shape_Area": 900000000.0, "gov": "GOV4", "dist": "GOV4_A", "sd": "AI49", "Nahya_EN": "AI49" }, "geometry": { "type": "Polygon", "coordinates": [ [ [ 38.8, 33.5 ], [ 38.8, 33.7 ], [ 39.2, 33.7 ], [ 39.2, 33.5 ], [ 38.8, 33.5 ] ] ] } },
{ "type": "Feature", "properties": { "OID_": 0, "PageName": "AI50", "PageNumber": 2310, "Shape_Leng": 120000.0, "Shape_Area": 900000000.0, "gov": "GOV3", "dist": "GOV3_A", "sd": "AI50", "Nahya_EN": "AI50" }, "geometry": { "type": "Polygon", "coordinates": [ [ [ 39.2, 33.5 ], [ 39.2, 33.7 ], [ 39.5, 33.7 ], [ 39.5, 33.5 ], [ 39.2, 33.5 ] ] ] } },
{ "type": "Feature", "properties": { "OID_": 0, "PageName": "AI51", "PageNumber": 2311, "Shape_Leng": 120000.0, "Shape_Area": 900000000.0, "gov": "GOV3", "dist": "GOV3_A", "sd": "AI51", "Nahya_EN": "AI51" }, "geometry": { "type": "Polygon", "coordinates": [ [ [ 39.5, 33.5 ], [ 39.5, 33.7 ], [ 39.8, 33.7 ], [ 39.8, 33.5 ], [ 39.5, 33.5 ] ] ] } },
{ "type": "Feature", "properties": { "OID_": 0, "PageName": "AI52", "PageNumber": 2312, "Shape_Leng": 120000.0, "Shape_Area": 900000000.0, "gov": "GOV3", "dist": "GOV3_A", "sd": "AI52", "Nahya_EN": "AI52" }, "geometry": { "type": "Polygon", "coordinates": [ [ [ 39.8, 33.5 ], [ 39.8, 33.7 ], [ 40.1, 33.7 ], [ 40.1, 33.5 ], [ 39.8, 33.5 ] ] ] } },
{ "type": "Feature", "properties": { "OID_": 0, "PageName": "AI53", "PageNumber": 2313, "Shape_Leng": 120000.0, "Shape_Area": 900000000.0, "gov": "GOV3", "dist": "GOV3_A", "sd": "AI53", "Nahya_EN": "AI53" }, "geometry": { "type": "Polygon", "coordinates": [ [ [ 40.1, 33.5 ], [ 40.1, 33.7 ], [ 40.5, 33.7 ], [ 40.4, 33.5 ], [ 40.1, 33.5 ] ] ] } },
{ "type": "Feature", "properties": { "OID_": 0, "PageName": "AI54", "PageNumber": 2314, "Shape_Leng": 120000.0, "Shape_Area": 900000000.0, "gov": "GOV3", "dist": "GOV3_A", "sd": "AI54", "Nahya_EN": "AI54" }, "geometry": { "type": "Polygon", "coordinates": [ [ [ 40.4, 33.5 ], [ 40.5, 33.7 ], [ 40.8, 33.7 ], [ 40.8, 33.5 ], [ 40.4, 33.5 ] ] ] } },
{ "type": "Feature", "properties": { "OID_": 0, "PageName": "AI55", "PageNumber": 2315, "Shape_Leng": 120000.0, "Shape_Area": 900000000.0, "gov": "GOV3", "dist": "GOV3_A", "sd": "AI55", "Nahya_EN": "AI55" }, "geometry": { "type": "Polygon", "coordinates": [ [ [ 40.8, 33.5 ], [ 40.8, 33.7 ], [ 41.1, 33.7 ], [ 41.1, 33.4 ], [ 40.8, 33.5 ] ] ] } },
{ "type": "Feature", "properties": { "OID_": 0, "PageName": "AI56", "PageNumber": 2316, "Shape_Leng": 120000.0, "Shape_Area": 900000000.0, "gov": "GOV3", "dist": "GOV3_A", "sd": "AI56", "Nahya_EN": "AI56" }, "geometry": { "type": "Polygon", "coordinates": [ [ [ 41.1, 33.4 ], [ 41.1, 33.7 ], [ 41.4, 33.7 ], [ 41.4, 33.4 ], [ 41.1, 33.4 ] ] ] } },
{ "type": "Feature", "properties": { "OID_": 0, "PageName": "AI57", "PageNumber": 2317, "Shape_Leng": 120000.0, "Shape_Area": 900000000.0, "gov": "GOV3", "dist": "GOV3_A", "sd": "AI57", "Nahya_EN": "AI57" }, "geometry": { "type": "Polygon", "coordinates": [ [ [ 41.4, 33.4 ], [ 41.4, 33.7 ], [ 41.7, 33.7 ], [ 41.7, 33.4 ], [ 41.4, 33.4 ] ] ] } },
{ "type": "Feature", "properties": { "OID_": 0, "PageName": "AI58", "PageNumber": 2318, "Shape_Leng": 120000.0, "Shape_Area": 900000000.0, "gov": "GOV3", "dist": "GOV3_A", "sd": "AI58", "Nahya_EN": "AI58" }, "geometry": { "type": "Polygon", "coordinates": [ [ [ 41.7, 33.4 ], [ 41.7, 33.7 ], [ 42.1, 33.7 ], [ 42.1, 33.4 ], [ 41.7, 33.4 ] ] ] } },
{ "type": "Feature", "properties": { "OID_": 0, "PageName": "AJ40", "PageNumber": 2385, "Shape_Leng": 120000.0, "Shape_Area": 900000000.0, "gov": "GOV4", "dist": "GOV4_A", "sd": "AJ40", "Nahya_EN": "AJ40" }, "geometry": { "type": "Polygon", "coordinates": [ [ [ 35.9, 33.2 ], [ 35.9, 33.4 ], [ 36.3, 33.4 ], [ 36.3, 33.2 ], [ 35.9, 33.2 ] ] ] } },
{ "type": "Feature", "properties": { "OID_": 0, "PageName": "AJ41", "PageNumber": 2386, "Shape_Leng": 120000.0, "Shape_Area": 900000000.0, "gov": "GOV4", "dist": "GOV4_A", "sd": "AJ41", "Nahya_EN": "AJ41" }, "geometry": { "type": "Polygon", "coordinates": [ [ [ 36.3, 33.2 ], [ 36.3, 33.4 ], [ 36.6, 33.4 ], [ 36.6, 33.2 ], [ 36.3, 33.2 ] ] ] } },
{ "type": "Feature", "properties": { "OID_": 0, "PageName": "AJ42", "PageNumber": 2387, "Shape_Leng": 120000.0, "Shape_Area": 900000000.0, "gov": "GOV4", "dist": "GOV4_A", "sd": "AJ42", "Nahya_EN": "AJ42" }, "geometry": { "type": "Polygon", "coordinates": [ [ [ 36.6, 33.2 ], [ 36.6, 33.4 ], [ 36.9, 33.4 ], [ 36.9, 33.2 ], [ 36.6, 33.2 ] ] ] } },
{ "type": "Feature", "properties": { "OID_": 0, "PageName": "AJ43", "PageNumber": 2388, "Shape_Leng": 120000.0, "Shape_Area": 900000000.0, "gov": "GOV4", "dist": "GOV4_A", "sd": "AJ43", "Nahya_EN": "AJ43" }, "geometry": { "type": "Polygon", "coordinates": [ [ [ 36.9, 33.2 ], [ 36.9, 33.4 ], [ 37.2, 33.5 ], [ 37.2, 33.2 ], [ 36.9, 33.2 ] ] ] } },
{ "type": "Feature", "properties": { "OID_": 0, "PageName": "AJ44", "PageNumber": 2389, "Shape_Leng": 120000.0, "Shape_Area": 900000000.0, "gov": "GOV4", "dist": "GOV4_A", "sd": "AJ44", "Nahya_EN": "AJ44" }, "geometry": { "type": "Polygon", "coordinates": [ [ [ 37.2, 33.2 ], [ 37.2, 33.5 ], [ 37.5, 33.5 ], [ 37.5, 33.2 ], [ 37.2, 33.2 ] ] ] } },
{ "type": "Feature", "properties": { "OID_": 0, "PageName": "AJ45", "PageNumber": 2390, "Shape_Leng": 120000.0, "Shape_Area": 900000000.0, "gov": "GOV4", "dist": "GOV4_A", "sd": "AJ45", "Nahya_EN": "AJ45" }, "geometry": { "type": "Polygon", "coordinates": [ [ [ 37.5, 33.2 ], [ 37.5, 33.5 ], [ 37.9, 33.5 ], [ 37.9, 33.2 ], [ 37.5, 33.2 ] ] ] } },
{ "type": "Feature", "properties": { "OID_": 0, "PageName": "AJ46", "PageNumber": 2391, "Shape_Leng": 120000.0, "Shape_Area": 900000000.0, "gov": "GOV4", "dist": "GOV4_A", "sd": "AJ46", "Nahya_EN": "AJ46" }, "geometry": { "type": "Polygon", "coordinates": [ [ [ 37.9, 33.2 ], [ 37.9, 33.5 ], [ 38.2, 33.5 ], [ 38.2, 33.2 ], [ 37.9, 33.2 ] ] ] } },
{ "type": "Feature", "properties": { "OID_": 0, "PageName": "AJ47", "PageNumber": 2392, "Shape_Leng": 120000.0, "Shape_Area": 900000000.0, "gov": "GOV4", "dist": "GOV4_A", "sd": "AJ47", "Nahya_EN": "AJ47" }, "geometry": { "type": "Polygon", "coordinates": [ [ [ 38.2, 33.2 ], [ 38.2, 33.5 ], [ 38.5, 33.5 ], [ 38.5, 33.2 ], [ 38.2, 33.2 ] ] ] } },
{ "type": "Feature", "properties": { "OID_": 0, "PageName": "AJ48", "PageNumber": 2393, "Shape_Leng": 120000.0, "Shape_Area": 900000000.0, "gov": "GOV4", "dist": "GOV4_A", "sd": "AJ48", "Nahya_EN": "AJ48" }, "geometry": { "type": "Polygon", "coordinates": [ [ [ 38.5, 33.2 ], [ 38.5, 33.5 ], [ 38.8, 33.5 ], [ 38.8, 33.2 ], [ 38.5, 33.2 ] ] ] } },
{ "type": "Feature", "properties": { "OID_": 0, "PageName": "AJ49", "PageNumber": 2394, "Shape_Leng": 120000.0, "Shape_Area": 900000000.0, "gov": "GOV4", "dist": "GOV4_A", "sd": "AJ49", "Nahya_EN": "AJ49" }, "geometry": { "type": "Polygon", "coordinates": [ [ [ 38.8, 33.2 ], [ 38.8, 33.5 ], [ 39.2, 33.5 ], [ 39.2, 33.2 ], [ 38.8, 33.2 ] ] ] } },
{ "type": "Feature", "properties": { "OID_": 0, "PageName": "AJ50", "PageNumber": 2395, "Shape_Leng": 120000.0, "Shape_Area": 900000000.0, "gov": "GOV3", "dist": "GOV3_A", "sd": "AJ50", "Nahya_EN": "AJ50" }, "geometry": { "type": "Polygon", "coordinates": [ [ [ 39.2, 33.2 ], [ 39.2, 33.5 ], [ 39.5, 33.5 ], [ 39.5, 33.2 ], [ 39.2, 33.2 ] ] ] } },
{ "type": "Feature", "properties": { "OID_": 0, "PageName": "AJ51", "PageNumber": 2396, "Shape_Leng": 120000.0, "Shape_Area": 900000000.0, "gov": "GOV3", "dist": "GOV3_A", "sd": "AJ51", "Nahya_EN": "AJ51" }, "geometry": { "type": "Polygon", "coordinates": [ [ [ 39.5, 33.2 ], [ 39.5, 33.5 ], [ 39.8, 33.5 ], [ 39.8, 33.2 ], [ 39.5, 33.2 ] ] ] } },
{ "type": "Feature", "properties": { "OID_": 0, "PageName": "AJ52", "PageNumber": 2397, "Shape_Leng": 120000.0, "Shape_Area": 900000000.0, "gov": "GOV3", "dist": "GOV3_A", "sd": "AJ52", "Nahya_EN": "AJ52" }, "geometry": { "type": "Polygon", "coordinates": [ [ [ 39.8, 33.2 ], [ 39.8, 33.5 ], [ 40.1, 33.5 ], [ 40.1, 33.2 ], [ 39.8, 33.2 ] ] ] } },
{ "type": "Feature", "properties": { "OID_": 0, "PageName": "AJ53", "PageNumber": 2398, "Shape_Leng": 120000.0, "Shape_Area": 900000000.0, "gov": "GOV3", "dist": "GOV3_A", "sd": "AJ53", "Nahya_EN": "AJ53" }, "geometry": { "type": "Polygon", "coordinates": [ [ [ 40.1, 33.2 ], [ 40.1, 33.5 ], [ 40.4, 33.5 ], [ 40.4, 33.2 ], [ 40.1, 33.2 ] ] ] } },
{ "type": "Feature", "properties": { "OID_": 0, "PageName": "AJ54", "PageNumber": 2399, "Shape_Leng": 120000.0, "Shape_Area": 900000000.0, "gov": "GOV3", "dist": "GOV3_A", "sd": "AJ54", "Nahya_EN": "AJ54" }, "geometry": { "type": "Polygon", "coordinates": [ [ [ 40.4, 33.2 ], [ 40.4, 33.5 ], [ 40.8, 33.5 ], [ 40.8, 33.2 ], [ 40.4, 33.2 ] ] ] } },
{ "type": "Feature", "properties": { "OID_": 0, "PageName": "AJ55", "PageNumber": 2400, "Shape_Leng": 120000.0, "Shape_Area": 900000000.0, "gov": "GOV3", "dist": "GOV3_A", "sd": "AJ55", "Nahya_EN": "AJ55" }, "geometry": { "type": "Polygon", "coordinates": [ [ [ 40.8, 33.2 ], [ 40.8, 33.5 ], [ 41.1, 33.4 ], [ 41.1, 33.2 ], [ 40.8, 33.2 ] ] ] } },
{ "type": "Feature", "properties": { "OID_": 0, "PageName": "AJ56", "PageNumber": 2401, "Shape_Leng": 120000.0, "Shape_Area": 900000000.0, "gov": "GOV3", "dist": "GOV3_A", "sd": "AJ56", "Nahya_EN": "AJ56" }, "geometry": { "type": "Polygon", "coordinates": [ [ [ 41.1, 33.2 ], [ 41.1, 33.4 ], [ 41.4, 33.4 ], [ 41.4, 33.2 ], [ 41.1, 33.2 ] ] ] } },
{ "type": "Feature", "properties": { "OID_": 0, "PageName": "AJ57", "PageNumber": 2402, "Shape_Leng": 120000.0, "Shape_Area": 900000000.0, "gov": "GOV3", "dist": "GOV3_A", "sd": "AJ57", "Nahya_EN": "AJ57" }, "geometry": { "type": "Polygon", "coordinates": [ [ [ 41.4, 33.2 ], [ 41.4, 33.4 ], [ 41.7, 33.4 ], [ 41.7, 33.2 ], [ 41.4, 33.2 ] ] ] } },
{ "type": "Feature", "properties": { "OID_": 0, "PageName": "AJ58", "PageNumber": 2403, "Shape_Leng": 120000.0, "Shape_Area": 900000000.0, "gov": "GOV3", "dist": "GOV3_A", "sd": "AJ58", "Nahya_EN": "AJ58" }, "geometry": { "type": "Polygon", "coordinates": [ [ [ 41.7, 33.2 ], [ 41.7, 33.4 ], [ 42.1, 33.4 ], [ 42.1, 33.2 ], [ 41.7, 33.2 ] ] ] } },
{ "type": "Feature", "properties": { "OID_": 0, "PageName": "AK40", "PageNumber": 2472, "Shape_Leng": 120000.0, "Shape_Area": 900000000.0, "gov": "GOV4", "dist": "GOV4_A", "sd": "AK40", "Nahya_EN": "AK40" }, "geometry": { "type": "Polygon", "coordinates": [ [ [ 35.9, 32.9 ], [ 35.9, 33.2 ], [ 36.3, 33.2 ], [ 36.3, 32.9 ], [ 35.9, 32.9 ] ] ] } },
{ "type": "Feature", "properties": { "OID_": 0, "PageName": "AK41", "PageNumber": 2473, "Shape_Leng": 120000.0, "Shape_Area": 900000000.0, "gov": "GOV4", "dist": "GOV4_A", "sd": "AK41", "Nahya_EN": "AK41" }, "geometry": { "type": "Polygon", "coordinates": [ [ [ 36.3, 32.9 ], [ 36.3, 33.2 ], [ 36.6, 33.2 ], [ 36.6, 32.9 ], [ 36.3, 32.9 ] ] ] } },
{ "type": "Feature", "properties": { "OID_": 0, "PageName": "AK42", "PageNumber": 2474, "Shape_Leng": 120000.0, "Shape_Area": 900000000.0, "gov": "GOV4", "dist": "GOV4_A", "sd": "AK42", "Nahya_EN": "AK42" }, "geometry": { "type": "Polygon", "coordinates": [ [ [ 36.6, 32.9 ], [ 36.6, 33.2 ], [ 36.9, 33.2 ], [ 36.9, 32.9 ], [ 36.6, 32.9 ] ] ] } },
{ "type": "Feature", "properties": { "OID_": 0, "PageName": "AK43", "PageNumber": 2475, "Shape_Leng": 120000.0, "Shape_Area": 900000000.0, "gov": "GOV4", "dist": "GOV4_A", "sd": "AK43", "Nahya_EN": "AK43" }, "geometry": { "type": "Polygon", "coordinates": [ [ [ 36.9, 32.9 ], [ 36.9, 33.2 ], [ 37.2, 33.2 ], [ 37.2, 32.9 ], [ 36.9, 32.9 ] ] ] } },
{ "type": "Feature", "properties": { "OID_": 0, "PageName": "AK44", "PageNumber": 2476, "Shape_Leng": 120000.0, "Shape_Area": 900000000.0, "gov": "GOV4", "dist": "GOV4_A", "sd": "AK44", "Nahya_EN": "AK44" }, "geometry": { "type": "Polygon", "coordinates": [ [ [ 37.2, 32.9 ], [ 37.2, 33.2 ], [ 37.5, 33.2 ], [ 37.6, 32.9 ], [ 37.2, 32.9 ] ] ] } },
{ "type": "Feature", "properties": { "OID_": 0, "PageName": "AK45", "PageNumber": 2477, "Shape_Leng": 120000.0, "Shape_Area": 900000000.0, "gov": "GOV4", "dist": "GOV4_A", "sd": "AK45", "Nahya_EN": "AK45" }, "geometry": { "type": "Polygon", "coordinates": [ [ [ 37.6, 32.9 ], [ 37.5, 33.2 ], [ 37.9, 33.2 ], [ 37.9, 32.9 ], [ 37.6, 32.9 ] ] ] } },
{ "type": "Feature", "properties": { "OID_": 0, "PageName": "AK46", "PageNumber": 2478, "Shape_Leng": 120000.0, "Shape_Area": 900000000.0, "gov": "GOV4", "dist": "GOV4_A", "sd": "AK46", "Nahya_EN": "AK46" }, "geometry": { "type": "Polygon", "coordinates": [ [ [ 37.9, 32.9 ], [ 37.9, 33.2 ], [ 38.2, 33.2 ], [ 38.2, 32.9 ], [ 37.9, 32.9 ] ] ] } },
{ "type": "Feature", "properties": { "OID_": 0, "PageName": "AK47", "PageNumber": 2479, "Shape_Leng": 120000.0, "Shape_Area": 900000000.0, "gov": "GOV4", "dist": "GOV4_A", "sd": "AK47", "Nahya_EN": "AK47" }, "geometry": { "type": "Polygon", "coordinates": [ [ [ 38.2, 32.9 ], [ 38.2, 33.2 ], [ 38.5, 33.2 ], [ 38.5, 32.9 ], [ 38.2, 32.9 ] ] ] } },
{ "type": "Feature", "properties": { "OID_": 0, "PageName": "AK48", "PageNumber": 2480, "Shape_Leng": 120000.0, "Shape_Area": 900000000.0, "gov": "GOV4", "dist": "GOV4_A", "sd": "AK48", "Nahya_EN": "AK48" }, "geometry": { "type": "Polygon", "coordinates": [ [ [ 38.5, 32.9 ], [ 38.5, 33.2 ], [ 38.8, 33.2 ], [ 38.8, 32.9 ], [ 38.5, 32.9 ] ] ] } },
{ "type": "Feature", "properties": { "OID_": 0, "PageName": "AK49", "PageNumber": 2481, "Shape_Leng": 120000.0, "Shape_Area": 900000000.0, "gov": "GOV4", "dist": "GOV4_A", "sd": "AK49", "Nahya_EN": "AK49" }, "geometry": { "type": "Polygon", "coordinates": [ [ [ 38.8, 32.9 ], [ 38.8, 33.2 ], [ 39.2, 33.2 ], [ 39.2, 32.9 ], [ 38.8, 32.9 ] ] ] } },
{ "type": "Feature", "properties": { "OID_": 0, "PageName": "AK50", "PageNumber": 2482, "Shape_Leng": 120000.0, "Shape_Area": 900000000.0, "gov": "GOV3", "dist": "GOV3_A", "sd": "AK50", "Nahya_EN": "AK50" }, "geometry": { "type": "Polygon", "coordinates": [ [ [ 39.2, 32.9 ], [ 39.2, 33.2 ], [ 39.5, 33.2 ], [ 39.5, 32.9 ], [ 39.2, 32.9 ] ] ] } },
{ "type": "Feature", "properties": { "OID_": 0, "PageName": "AK51", "PageNumber": 2483, "Shape_Leng": 120000.0, "Shape_Area": 900000000.0, "gov": "GOV3", "dist": "GOV3_A", "sd": "AK51", "Nahya_EN": "AK51" }, "geometry": { "type": "Polygon", "coordinates": [ [ [ 39.5, 32.9 ], [ 39.5, 33.2 ], [ 39.8, 33.2 ], [ 39.8, 32.9 ], [ 39.5, 32.9 ] ] ] } },
{ "type": "Feature", "properties": { "OID_": 0, "PageName": "AK52", "PageNumber": 2484, "Shape_Leng": 120000.0, "Shape_Area": 900000000.0, "gov": "GOV3", "dist": "GOV3_A", "sd": "AK52", "Nahya_EN": "AK52" }, "geometry": { "type": "Polygon", "coordinates": [ [ [ 39.8, 32.9 ], [ 39.8, 33.2 ], [ 40.1, 33.2 ], [ 40.1, 32.9 ], [ 39.8, 32.9 ] ] ] } },
{ "type": "Feature", "properties": { "OID_": 0, "PageName": "AK53", "PageNumber": 2485, "Shape_Leng": 120000.0, "Shape_Area": 900000000.0, "gov": "GOV3", "dist": "GOV3_A", "sd": "AK53", "Nahya_EN": "AK53" }, "geometry": { "type": "Polygon", "coordinates": [ [ [ 40.1, 32.9 ], [ 40.1, 33.2 ], [ 40.4, 33.2 ], [ 40.4, 32.9 ], [ 40.1, 32.9 ] ] ] } },
{ "type": "Feature", "properties": { "OID_": 0, "PageName": "AK54", "PageNumber": 2486, "Shape_Leng": 120000.0, "Shape_Area": 900000000.0, "gov": "GOV3", "dist": "GOV3_A", "sd": "AK54", "Nahya_EN": "AK54" }, "geometry": { "type": "Polygon", "coordinates": [ [ [ 40.4, 32.9 ], [ 40.4, 33.2 ], [ 40.8, 33.2 ], [ 40.8, 32.9 ], [ 40.4, 32.9 ] ] ] } },
{ "type": "Feature", "properties": { "OID_": 0, "PageName": "AK55", "PageNumber": 2487, "Shape_Leng": 120000.0, "Shape_Area": 900000000.0, "gov": "GOV3", "dist": "GOV3_A", "sd": "AK55", "Nahya_EN": "AK55" }, "geometry": { "type": "Polygon", "coordinates": [ [ [ 40.8, 32.9 ], [ 40.8, 33.2 ], [ 41.1, 33.2 ], [ 41.1, 32.9 ], [ 40.8, 32.9 ] ] ] } },
{ "type": "Feature", "properties": { "OID_": 0, "PageName": "AK56", "PageNumber": 2488, "Shape_Leng": 120000.0, "Shape_Area": 900000000.0, "gov": "GOV3", "dist": "GOV3_A", "sd": "AK56", "Nahya_EN": "AK56" }, "geometry": { "type": "Polygon", "coordinates": [ [ [ 41.1, 32.9 ], [ 41.1, 33.2 ], [ 41.4, 33.2 ], [ 41.4, 32.9 ], [ 41.1, 32.9 ] ] ] } },
{ "type": "Feature", "properties": { "OID_": 0, "PageName": "AK57", "PageNumber": 2489, "Shape_Leng": 120000.0, "Shape_Area": 900000000.0, "gov": "GOV3", "dist": "GOV3_A", "sd": "AK57", "Nahya_EN": "AK57" }, "geometry": { "type": "Polygon", "coordinates": [ [ [ 41.4, 32.9 ], [ 41.4, 33.2 ], [ 41.7, 33.2 ], [ 41.7, 32.9 ], [ 41.4, 32.9 ] ] ] } },
{ "type": "Feature", "properties": { "OID_": 0, "PageName": "AK58", "PageNumber": 2490, "Shape_Leng": 120000.0, "Shape_Area": 900000000.0, "gov": "GOV3", "dist": "GOV3_A", "sd": "AK58", "Nahya_EN": "AK58" }, "geometry": { "type": "Polygon", "coordinates": [ [ [ 41.7, 32.9 ], [ 41.7, 33.2 ], [ 42.1, 33.2 ], [ 42.0, 32.9 ], [ 41.7, 32.9 ] ] ] } }
]
}
